Workbook
Name Description: Summary!$B$15
Name Div01_General_Requirements: DivisionCostCodeLookup!$F$2:$F$22
Name Div02_Existing_Conditions: DivisionCostCodeLookup!$F$23:$F$36
Name Div03_Concrete: DivisionCostCodeLookup!$F$37:$F$44
Name Div04_Masonry: DivisionCostCodeLookup!$F$45:$F$51
Name Div05_Metals: DivisionCostCodeLookup!$F$52:$F$65
Name Div06_Wood_Plastics_And_Composites: DivisionCostCodeLookup!$F$66:$F$79
Name Div07_Thermaland_Moisture_Protection: DivisionCostCodeLookup!$F$80:$F$104
Name Div08_Openings: DivisionCostCodeLookup!$F$105:$F$125
Name Div09_Finishes: DivisionCostCodeLookup!$F$126:$F$157
Name Div10_Specialties: DivisionCostCodeLookup!$F$158:$F$173
Name Div11_Equipment: DivisionCostCodeLookup!$F$174:$F$182
Name Div12_Furnishings: DivisionCostCodeLookup!$F$183:$F$193
Name Div13_Special_Construction: DivisionCostCodeLookup!$F$194:$F$197
Name Div14_Conveying_Equipment: DivisionCostCodeLookup!$F$198:$F$204
Name Div21_Fire_Suppression: DivisionCostCodeLookup!$F$205:$F$219
Name Div22_Plumbing: DivisionCostCodeLookup!$F$220:$F$236
Name Div23_Heating_Ventilating_And_Air_Conditioning: DivisionCostCodeLookup!$F$237:$F$278
Name Div26_Electrical: DivisionCostCodeLookup!$F$279:$F$308
Name Div27_Communications: DivisionCostCodeLookup!$F$309:$F$328
Name Div28_Electronic_Safety_And_Security: DivisionCostCodeLookup!$F$329:$F$339
Name Div31_Earthwork: DivisionCostCodeLookup!$F$340:$F$353
Name Div32_Exterior_Improvements: DivisionCostCodeLookup!$F$354:$F$383
Name Div33_Utilities: DivisionCostCodeLookup!$F$384:$F$391
Name Div34_Transportation: DivisionCostCodeLookup!$F$392:$F$409
Name Div35_Waterway_And_Marine: DivisionCostCodeLookup!$F$410:$F$423
Name Div41_Material_Proc_And_Handling_Eq.: DivisionCostCodeLookup!$F$424:$F$426
Name Div51_Earthwork_FAA: DivisionCostCodeLookup!$F$428:$F$438
Name Div52_Flexible_Base_Courses_FAA: DivisionCostCodeLookup!$F$439:$F$447
Name Div53_Rigid_Base_Courses_FAA: DivisionCostCodeLookup!$F$448:$F$452
Name Div54_Flexible_Surface_Courses_FAA: DivisionCostCodeLookup!$F$453:$F$457
Name Div55_Rigid_Pavement_FAA: DivisionCostCodeLookup!$F$458:$F$460
Name Div56_Miscellaneous_FAA: DivisionCostCodeLookup!$F$461:$F$474
Name Div57_Fencing_FAA: DivisionCostCodeLookup!$F$475:$F$480
Name Div58_Drainage_FAA: DivisionCostCodeLookup!$F$481:$F$488
Name Div59_Turfing_FAA: DivisionCostCodeLookup!$F$489:$F$496
Name Div60_Lighting_Installation_FAA: DivisionCostCodeLookup!$F$497:$F$507
Name DivisionDescription: DivisionCostCodeLookup!$A$2:$A$37
Name DivisionSummaryList: DivisionCostCodeLookup!$L$2:$L$12
Name EstimateTotal: Summary!$C$34
Name HardCostSubTotal: Summary!$C$21
Name HCostForm: 'Hard Cost Estimate Form'!$H$5
Name projectStage: Summary!$B$12
Name RevNotes: Summary!$B$19
Name Scope: Summary!$B$17
Name ScopeAccuracy: 'Scope and Risk'!$C$3:$C$5
Name SCostForm: 'Optional - Sch & Resource Form'!$G$5
Name SCostForm: 'Soft Cost Estimating Form'!$L$5
Name SoftCostSubtotal: Summary!$C$23
Name SoftCostUoM: SoftCostUom!$G$2:$G$7
Name SoftCostUoM: SoftCostUom!$G$2:$G$8
Name UoM: SoftCostUom!$C$2:$C$15
Name UoM: UoM!$C$2:$C$16

Sheet Summary
B2: =IF(B12<>"", B12, "Estimate Summary") -> Estimate Summary
C3: : Project Title
C4: : Project Number
C5: : Originator
C6: : Project Manager (If Assigned)
C7: : Reviewer/Approver
C8: : Date (Last Revised)
C9: : Revision#
C10: : Scope Accuracy
C11: : Engineering Effort
C12: : Project Stage
B14: SCOPE DESCRIPTION:
B16: SCOPE ASSUMPTIONS AND CLARIFICATIONS:
B18: REVISION NOTES:
B21: HARD COST SUBTOTAL | C21: =HCostForm -> 0
B23: SOFT COST SUBTOTAL | C23: =SCostForm -> 0
B25: HARD COST CONTINGENCY | C25: =C26*C21 -> 0
B26: (Enter % of Hard Cost):
B28: SOFT COST CONTINGENCY | C28: =C29*C23 -> 0
B29: (Enter % of Soft Cost):
B31: ESCALATION | C31: =IFERROR((C21+C23+C25+C28)*C135,0) -> 0
B32: Based on Calculations Below Under "Escalation Calculator" : | C32: =C135
B34: TOTAL PROJECT ESTIMATE | C34: =C21+C23+C25+C28+C31 -> 0
B36: Hard Cost Summary
B37: HARD COST DESCRIPTION | C37: TOTAL
B38: 01 General Requirements | C38: =SUMIF('Hard Cost Estimate Form'!$A$8:$A$1000,B38,'Hard Cost Estimate Form'!$H$8:$H$1000) -> 0
B39: 02 Existing Conditions | C39: =SUMIF('Hard Cost Estimate Form'!$A$8:$A$1000,B39,'Hard Cost Estimate Form'!$H$8:$H$1000) -> 0
B40: 03 Concrete | C40: =SUMIF('Hard Cost Estimate Form'!$A$8:$A$1000,B40,'Hard Cost Estimate Form'!$H$8:$H$1000) -> 0
B41: 04 Masonry | C41: =SUMIF('Hard Cost Estimate Form'!$A$8:$A$1000,B41,'Hard Cost Estimate Form'!$H$8:$H$1000) -> 0
B42: 05 Metals | C42: =SUMIF('Hard Cost Estimate Form'!$A$8:$A$1000,B42,'Hard Cost Estimate Form'!$H$8:$H$1000) -> 0
B43: 06 Wood Plastics And Composites | C43: =SUMIF('Hard Cost Estimate Form'!$A$8:$A$1000,B43,'Hard Cost Estimate Form'!$H$8:$H$1000) -> 0
B44: 07 Thermaland Moisture Protection | C44: =SUMIF('Hard Cost Estimate Form'!$A$8:$A$1000,B44,'Hard Cost Estimate Form'!$H$8:$H$1000) -> 0
B45: 08 Openings | C45: =SUMIF('Hard Cost Estimate Form'!$A$8:$A$1000,B45,'Hard Cost Estimate Form'!$H$8:$H$1000) -> 0
B46: 09 Finishes | C46: =SUMIF('Hard Cost Estimate Form'!$A$8:$A$1000,B46,'Hard Cost Estimate Form'!$H$8:$H$1000) -> 0
B47: 10 Specialties | C47: =SUMIF('Hard Cost Estimate Form'!$A$8:$A$1000,B47,'Hard Cost Estimate Form'!$H$8:$H$1000) -> 0
B48: 11 Equipment | C48: =SUMIF('Hard Cost Estimate Form'!$A$8:$A$1000,B48,'Hard Cost Estimate Form'!$H$8:$H$1000) -> 0
B49: 12 Furnishings | C49: =SUMIF('Hard Cost Estimate Form'!$A$8:$A$1000,B49,'Hard Cost Estimate Form'!$H$8:$H$1000) -> 0
... B73: 60 Lighting Installation FAA | C73: =SUMIF('Hard Cost Estimate Form'!$A$8:$A$1000,B73,'Hard Cost Estimate Form'!$H$8:$H$1000) -> 0
B74: Misc - Not Listed | C74: =SUM('Hard Cost Estimate Form'!$H$8:$H$1000)-SUM(C38:C73) -> 0
B75: 1 | C75: 1
B76: Soft Cost Summary
B80: 101000 - Project Admin & Mgmt-General | C80: ='Soft Cost Estimating Form'!L8 -> 0
B81: 101400 - Project Admin & Mgmt-Design | C81: ='Soft Cost Estimating Form'!L9 -> 0
B82: 101500 - Project Admin & Mgmt-Construction | C82: ='Soft Cost Estimating Form'!L10 -> 0
B83: 141010 - Design-Outside Design Services | C83: ='Soft Cost Estimating Form'!L11 -> 0
B84: 141100 - Design-Specification Development | C84: ='Soft Cost Estimating Form'!L12 -> 0
B85: 141600 - Design-Environmental | C85: ='Soft Cost Estimating Form'!L13 -> 0
B86: 141700 - Design-PE Design | C86: ='Soft Cost Estimating Form'!L14 -> 0
B87: 141800 - Design-Survey | C87: ='Soft Cost Estimating Form'!L15 -> 0
B88: 141900 - Design-Drawing and Development | C88: ='Soft Cost Estimating Form'!L16 -> 0
B89: 142100 - Design-Construction/Inspection Suppor | C89: ='Soft Cost Estimating Form'!L17 -> 0
B90: 142600 - Design-IT Design Support | C90: ='Soft Cost Estimating Form'!L18 -> 0
B91: 171500 - Development-Conceptual Design | C91: ='Soft Cost Estimating Form'!L19 -> 0
... B108: 909000 - Capitalized Alloc Sup Svs-Capitalized Allocated Supp Svs | C108: ='Soft Cost Estimating Form'!L36 -> 0
B109: Misc - Not Listed | C109: =SUM('Soft Cost Estimating Form'!L8:L740)-SUM(C80:C108) -> 0
B111: Escalation Calculator
B113: Base Escalation Rate (Yearly):
B115: Date of Estimate:
B117: Construction Start:
B119: Construction Finish:
B121: Construction Midpoint: | C121: =IFERROR(MEDIAN(C117,C119),"")
B123: Est. Date to Const. Start: | C123: =IFERROR(C117-C115,"") -> 0
C124: =IFERROR(C123/30.4167,"") -> 0
C125: =IFERROR(C123/365,"") -> 0
B127: Const. Start to Midpoint: | C127: =IFERROR(C121-C117,"")
C128: =IFERROR(C127/30.4167,"")
C129: =IFERROR(C127/365,"")
B131: Estimate Date to Midpoint: | C131: =IFERROR(C121-C115,"")
C132: =IFERROR(C131/30.4167,"")
C133: =IFERROR(C131/365,"")
B135: Escalation: | C135: =IFERROR(C113*C133,"")

Sheet Hard Cost Estimate Form
A1: Hard Cost Estimating Form (Details)
A2: Project Title: | B2: =IF(Summary!B3<>"",Summary!B3,"") | D2: Instructions:
A3: Project #: | B3: =IF(Summary!B4<>"",Summary!B4,"") | D3: Step 1: Select Division from Dropdown in Column A to Populate Options in Column B
A4: Rev #: | B4: =IF(Summary!B9<>"",Summary!B9,"") | D4: Step 2: Select Associated Cost Code Description from Dropdown in Column B [Optional]
A5: Rev # Date: | B5: =IF(Summary!B8<>"",Summary!B8,"") | D5: Step 3: Fill in Estimating Table in Columns (D to G) | G5: Hard Cost Total: | H5: =SUM(H8:H1048576) -> 0
A7: Division | B7: Cost Code Description | C7: Cost Code | D7: Item Description | E7: QTY | F7: Unit | G7: Unit Rate | H7: Total
C8: =IF(A8<>"",IFERROR(VLOOKUP(B8,DivisionCostCodeLookup!$F$2:$G$426,2,FALSE),INT(LEFT(A8,2))&"0000"),"") | H8: =IF(E8*G8<>0,E8*G8,"")
C9: =IF(A9<>"",IFERROR(VLOOKUP(B9,DivisionCostCodeLookup!$F$2:$G$426,2,FALSE),INT(LEFT(A9,2))&"0000"),"") | H9: =IF(E9*G9<>0,E9*G9,"")
C10: =IF(A10<>"",IFERROR(VLOOKUP(B10,DivisionCostCodeLookup!$F$2:$G$426,2,FALSE),INT(LEFT(A10,2))&"0000"),"") | H10: =IF(E10*G10<>0,E10*G10,"")
C11: =IF(A11<>"",IFERROR(VLOOKUP(B11,DivisionCostCodeLookup!$F$2:$G$426,2,FALSE),INT(LEFT(A11,2))&"0000"),"") | H11: =IF(E11*G11<>0,E11*G11,"")
C12: =IF(A12<>"",IFERROR(VLOOKUP(B12,DivisionCostCodeLookup!$F$2:$G$426,2,FALSE),INT(LEFT(A12,2))&"0000"),"") | H12: =IF(E12*G12<>0,E12*G12,"")
C13: =IF(A13<>"",IFERROR(VLOOKUP(B13,DivisionCostCodeLookup!$F$2:$G$426,2,FALSE),INT(LEFT(A13,2))&"0000"),"") | H13: =IF(E13*G13<>0,E13*G13,"")
C14: =IF(A14<>"",IFERROR(VLOOKUP(B14,DivisionCostCodeLookup!$F$2:$G$426,2,FALSE),INT(LEFT(A14,2))&"0000"),"") | H14: =IF(E14*G14<>0,E14*G14,"")
C15: =IF(A15<>"",IFERROR(VLOOKUP(B15,DivisionCostCodeLookup!$F$2:$G$426,2,FALSE),INT(LEFT(A15,2))&"0000"),"") | H15: =IF(E15*G15<>0,E15*G15,"")
C16: =IF(A16<>"",IFERROR(VLOOKUP(B16,DivisionCostCodeLookup!$F$2:$G$426,2,FALSE),INT(LEFT(A16,2))&"0000"),"") | H16: =IF(E16*G16<>0,E16*G16,"")
C17: =IF(A17<>"",IFERROR(VLOOKUP(B17,DivisionCostCodeLookup!$F$2:$G$426,2,FALSE),INT(LEFT(A17,2))&"0000"),"") | H17: =IF(E17*G17<>0,E17*G17,"")
C18: =IF(A18<>"",IFERROR(VLOOKUP(B18,DivisionCostCodeLookup!$F$2:$G$426,2,FALSE),INT(LEFT(A18,2))&"0000"),"") | H18: =IF(E18*G18<>0,E18*G18,"")
C19: =IF(A19<>"",IFERROR(VLOOKUP(B19,DivisionCostCodeLookup!$F$2:$G$426,2,FALSE),INT(LEFT(A19,2))&"0000"),"") | H19: =IF(E19*G19<>0,E19*G19,"")
... C74: =IF(A74<>"",IFERROR(VLOOKUP(B74,DivisionCostCodeLookup!$F$2:$G$426,2,FALSE),INT(LEFT(A74,2))&"0000"),"") | H74: =IF(E74*G74<>0,E74*G74,"")
A75: 02 Existing Conditions | B75: AsbestosAbatement | C75: =IF(A75<>"",IFERROR(VLOOKUP(B75,DivisionCostCodeLookup!$F$2:$G$426,2,FALSE),INT(LEFT(A75,2))&"0000"),"") -> 28213 | H75: =IF(E75*G75<>0,E75*G75,"")
C76: =IF(A76<>"",IFERROR(VLOOKUP(B76,DivisionCostCodeLookup!$F$2:$G$426,2,FALSE),INT(LEFT(A76,2))&"0000"),"") | H76: =IF(E76*G76<>0,E76*G76,"")
C77: =IF(A77<>"",IFERROR(VLOOKUP(B77,DivisionCostCodeLookup!$F$2:$G$426,2,FALSE),INT(LEFT(A77,2))&"0000"),"") | H77: =IF(E77*G77<>0,E77*G77,"")
C78: =IF(A78<>"",IFERROR(VLOOKUP(B78,DivisionCostCodeLookup!$F$2:$G$426,2,FALSE),INT(LEFT(A78,2))&"0000"),"") | H78: =IF(E78*G78<>0,E78*G78,"")
C79: =IF(A79<>"",IFERROR(VLOOKUP(B79,DivisionCostCodeLookup!$F$2:$G$426,2,FALSE),INT(LEFT(A79,2))&"0000"),"") | H79: =IF(E79*G79<>0,E79*G79,"")
C80: =IF(A80<>"",IFERROR(VLOOKUP(B80,DivisionCostCodeLookup!$F$2:$G$426,2,FALSE),INT(LEFT(A80,2))&"0000"),"") | H80: =IF(E80*G80<>0,E80*G80,"")
C81: =IF(A81<>"",IFERROR(VLOOKUP(B81,DivisionCostCodeLookup!$F$2:$G$426,2,FALSE),INT(LEFT(A81,2))&"0000"),"") | H81: =IF(E81*G81<>0,E81*G81,"")
C82: =IF(A82<>"",IFERROR(VLOOKUP(B82,DivisionCostCodeLookup!$F$2:$G$426,2,FALSE),INT(LEFT(A82,2))&"0000"),"") | H82: =IF(E82*G82<>0,E82*G82,"")
C83: =IF(A83<>"",IFERROR(VLOOKUP(B83,DivisionCostCodeLookup!$F$2:$G$426,2,FALSE),INT(LEFT(A83,2))&"0000"),"") | H83: =IF(E83*G83<>0,E83*G83,"")
C84: =IF(A84<>"",IFERROR(VLOOKUP(B84,DivisionCostCodeLookup!$F$2:$G$426,2,FALSE),INT(LEFT(A84,2))&"0000"),"") | H84: =IF(E84*G84<>0,E84*G84,"")
C85: =IF(A85<>"",IFERROR(VLOOKUP(B85,DivisionCostCodeLookup!$F$2:$G$426,2,FALSE),INT(LEFT(A85,2))&"0000"),"") | H85: =IF(E85*G85<>0,E85*G85,"")
C86: =IF(A86<>"",IFERROR(VLOOKUP(B86,DivisionCostCodeLookup!$F$2:$G$426,2,FALSE),INT(LEFT(A86,2))&"0000"),"") | H86: =IF(E86*G86<>0,E86*G86,"")
C87: =IF(A87<>"",IFERROR(VLOOKUP(B87,DivisionCostCodeLookup!$F$2:$G$426,2,FALSE),INT(LEFT(A87,2))&"0000"),"") | H87: =IF(E87*G87<>0,E87*G87,"")
... C1000: =IF(A1000<>"",IFERROR(VLOOKUP(B1000,DivisionCostCodeLookup!$F$2:$G$426,2,FALSE),INT(LEFT(A1000,2))&"0000"),"") | H1000: =IF(E1000*G1000<>0,E1000*G1000,"")

Sheet Soft Cost Estimating Form
A1: Soft Cost Estimating Form (Details) | AA1: =SUM(J8,J12,J13,J14,J15,J16,J17,J18,J21,J22,J24,J25,J26,J28,J29,J31,J32,J33,J34,J36)-'Optional - Sch & Resource Form'!C89 -> 0
B2: Project Title: | D2: =IF(Summary!B3<>"",Summary!B3,"")
B3: Project #: | D3: =IF(Summary!B4<>"",Summary!B4,"") | K3: Estimating Method | L3: Percentage Based
B4: Rev #: | D4: =IF(Summary!B9<>"",Summary!B9,"") | K4: Soft Cost %
B5: Rev # Date: | D5: =IF(Summary!B8<>"",Summary!B8,"") | K5: Soft Cost Total: | L5: =IF(L3="Percentage Based",L4*HardCostSubTotal,SUM(L8:L1048576)) -> 0
A7: Chart Type | B7: Chart Name | C7: Description | D7: Cost Code | E7: Description | F7: Container | G7: Container Description | H7: Interdepartmental Labor | I7: Total Unit Rate | J7: Qty | K7: Unit | L7: Total
A8: M01 | B8: Engineering Standard | C8: =B8 & " - " & LEFT(E8,FIND("-",E8)-1) -> Engineering Standard - Project Admin & Mgmt | D8: 101000 | E8: Project Admin & Mgmt-General | F8: M02 | G8: General Administration | H8: LBR | I8: 186 | J8: ='Optional - Sch & Resource Form'!C17 -> 0 | K8: Hr | L8: =I8*J8 -> 0
A9: M01 | B9: Engineering Standard | C9: =B9 & " - " & LEFT(E9,FIND("-",E9)-1) -> Engineering Standard - Project Admin & Mgmt | D9: 101400 | E9: Project Admin & Mgmt-Design | F9: M02 | G9: General Administration | H9: LBR | I9: 186 | L9: =I9*J9 -> 0
A10: M01 | B10: Engineering Standard | C10: =B10 & " - " & LEFT(E10,FIND("-",E10)-1) -> Engineering Standard - Project Admin & Mgmt | D10: 101500 | E10: Project Admin & Mgmt-Construction | F10: M02 | G10: General Administration | H10: LBR | I10: 186 | L10: =I10*J10 -> 0
A11: M01 | B11: Engineering Standard | C11: =B11 & " - " & LEFT(E11,FIND("-",E11)-1) -> Engineering Standard - Design | D11: 141010 | E11: Design-Outside Design Services | F11: M03 | G11: Design | L11: =I11*J11 -> 0
A12: M01 | B12: Engineering Standard | C12: =B12 & " - " & LEFT(E12,FIND("-",E12)-1) -> Engineering Standard - Design | D12: 141100 | E12: Design-Specification Development | F12: M03 | G12: Design | H12: LBR | I12: 158 | J12: ='Optional - Sch & Resource Form'!C20 -> 0 | K12: Hr | L12: =I12*J12 -> 0
A13: M01 | B13: Engineering Standard | C13: =B13 & " - " & LEFT(E13,FIND("-",E13)-1) -> Engineering Standard - Design | D13: 141600 | E13: Design-Environmental | F13: M03 | G13: Design | H13: LBR | I13: 126 | J13: ='Optional - Sch & Resource Form'!C23 -> 0 | K13: Hr | L13: =I13*J13 -> 0
A14: M01 | B14: Engineering Standard | C14: =B14 & " - " & LEFT(E14,FIND("-",E14)-1) -> Engineering Standard - Design | D14: 141700 | E14: Design-PE Design | F14: M03 | G14: Design | H14: LBR | I14: 158 | J14: ='Optional - Sch & Resource Form'!C28 -> 0 | K14: Hr | L14: =I14*J14 -> 0
A15: M01 | B15: Engineering Standard | C15: =B15 & " - " & LEFT(E15,FIND("-",E15)-1) -> Engineering Standard - Design | D15: 141800 | E15: Design-Survey | F15: M03 | G15: Design | H15: LBR | I15: 158 | J15: ='Optional - Sch & Resource Form'!C32 -> 0 | K15: Hr | L15: =I15*J15 -> 0
A16: M01 | B16: Engineering Standard | C16: =B16 & " - " & LEFT(E16,FIND("-",E16)-1) -> Engineering Standard - Design | D16: 141900 | E16: Design-Drawing and Development | F16: M03 | G16: Design | H16: LBR | I16: 158 | J16: ='Optional - Sch & Resource Form'!C37 -> 0 | K16: Hr | L16: =I16*J16 -> 0
A17: M01 | B17: Engineering Standard | C17: =B17 & " - " & LEFT(E17,FIND("-",E17)-1) -> Engineering Standard - Design | D17: 142100 | E17: Design-Construction/Inspection Suppor | F17: M03 | G17: Design | H17: LBR | I17: 147 | J17: ='Optional - Sch & Resource Form'!C41 -> 0 | K17: Hr | L17: =I17*J17 -> 0
A18: M01 | B18: Engineering Standard | C18: =B18 & " - " & LEFT(E18,FIND("-",E18)-1) -> Engineering Standard - Design | D18: 142600 | E18: Design-IT Design Support | F18: M03 | G18: Design | H18: LBR | I18: 145 | J18: ='Optional - Sch & Resource Form'!C44 -> 0 | K18: Hr | L18: =I18*J18 -> 0
A19: M01 | B19: Engineering Standard | C19: =B19 & " - " & LEFT(E19,FIND("-",E19)-1) -> Engineering Standard - Development | D19: 171500 | E19: Development-Conceptual Design | F19: M03 | G19: Design | H19: LBR | L19: =I19*J19 -> 0
A20: M01 | B20: Engineering Standard | C20: =B20 & " - " & LEFT(E20,FIND("-",E20)-1) -> Engineering Standard - Construction | D20: 191100 | E20: Construction-Equipment Contracts | F20: M04 | G20: Execute/Build | H20: LBR | L20: =I20*J20 -> 0
A21: M01 | B21: Engineering Standard | C21: =B21 & " - " & LEFT(E21,FIND("-",E21)-1) -> Engineering Standard - Construction | D21: 191200 | E21: Construction-Management | F21: M04 | G21: Execute/Build | H21: LBR | I21: 170 | J21: ='Optional - Sch & Resource Form'!C47 -> 0 | K21: Hr | L21: =I21*J21 -> 0
A22: M01 | B22: Engineering Standard | C22: =B22 & " - " & LEFT(E22,FIND("-",E22)-1) -> Engineering Standard - Construction | D22: 191300 | E22: Construction-Inspection | F22: M04 | G22: Execute/Build | H22: LBR | I22: 147 | J22: ='Optional - Sch & Resource Form'!C52 -> 0 | K22: Hr | L22: =I22*J22 -> 0
A23: M01 | B23: Engineering Standard | C23: =B23 & " - " & LEFT(E23,FIND("-",E23)-1) -> Engineering Standard - Construction | D23: 191400 | E23: Construction-Testing | F23: M04 | G23: Execute/Build | H23: LBR | L23: =I23*J23 -> 0
A24: M01 | B24: Engineering Standard | C24: =B24 & " - " & LEFT(E24,FIND("-",E24)-1) -> Engineering Standard - Construction | D24: 191500 | E24: Construction-Survey | F24: M04 | G24: Execute/Build | H24: LBR | I24: 158 | J24: ='Optional - Sch & Resource Form'!C56 -> 0 | K24: Hr | L24: =I24*J24 -> 0
A25: M01 | B25: Engineering Standard | C25: =B25 & " - " & LEFT(E25,FIND("-",E25)-1) -> Engineering Standard - Construction | D25: 191600 | E25: Construction-Environmental | F25: M04 | G25: Execute/Build | H25: LBR | I25: 132 | J25: ='Optional - Sch & Resource Form'!C59 -> 0 | K25: Hr | L25: =I25*J25 -> 0
A26: M01 | B26: Engineering Standard | C26: =B26 & " - " & LEFT(E26,FIND("-",E26)-1) -> Engineering Standard - Construction | D26: 191800 | E26: Construction-Engineering Support | F26: M04 | G26: Execute/Build | H26: LBR | I26: 158 | J26: ='Optional - Sch & Resource Form'!C64 -> 0 | K26: Hr | L26: =I26*J26 -> 0
A27: M01 | B27: Engineering Standard | C27: =B27 & " - " & LEFT(E27,FIND("-",E27)-1) -> Engineering Standard - Construction | D27: 191810 | E27: Construction-Outside Construction Services | F27: M04 | G27: Execute/Build | L27: =I27*J27 -> 0
A28: M01 | B28: Engineering Standard | C28: =B28 & " - " & LEFT(E28,FIND("-",E28)-1) -> Engineering Standard - Construction | D28: 191900 | E28: Construction-Maintenance | F28: M04 | G28: Execute/Build | H28: LBR | I28: 147 | J28: ='Optional - Sch & Resource Form'!C67 -> 0 | K28: Hr | L28: =I28*J28 -> 0
A29: M01 | B29: Engineering Standard | C29: =B29 & " - " & LEFT(E29,FIND("-",E29)-1) -> Engineering Standard - Construction | D29: 192000 | E29: Construction-IT | F29: M04 | G29: Execute/Build | H29: LBR | I29: 145 | J29: ='Optional - Sch & Resource Form'!C70 -> 0 | K29: Hr | L29: =I29*J29 -> 0
A30: M01 | B30: Engineering Standard | C30: =B30 & " - " & LEFT(E30,FIND("-",E30)-1) -> Engineering Standard - Permitting | D30: 201400 | E30: Permitting-City | F30: M02 | G30: General Administration | H30: LBR | L30: =I30*J30 -> 0
A31: M01 | B31: Engineering Standard | C31: =B31 & " - " & LEFT(E31,FIND("-",E31)-1) -> Engineering Standard - Project Close Out | D31: 781100 | E31: Project Close Out-As Builts | F31: M05 | G31: Close-out | H31: LBR | I31: 141 | J31: ='Optional - Sch & Resource Form'!C75 -> 0 | K31: Hr | L31: =I31*J31 -> 0
A32: M01 | B32: Engineering Standard | C32: =B32 & " - " & LEFT(E32,FIND("-",E32)-1) -> Engineering Standard - Project Close Out | D32: 781200 | E32: Project Close Out-Survey | F32: M05 | G32: Close-out | H32: LBR | I32: 158 | J32: ='Optional - Sch & Resource Form'!C78 -> 0 | K32: Hr | L32: =I32*J32 -> 0
A33: M01 | B33: Engineering Standard | C33: =B33 & " - " & LEFT(E33,FIND("-",E33)-1) -> Engineering Standard - Project Close Out | D33: 781300 | E33: Project Close Out-Technical Reference Center | F33: M05 | G33: Close-out | H33: LBR | I33: 141 | J33: ='Optional - Sch & Resource Form'!C81 -> 0 | K33: Hr | L33: =I33*J33 -> 0
A34: M01 | B34: Engineering Standard | C34: =B34 & " - " & LEFT(E34,FIND("-",E34)-1) -> Engineering Standard - Project Close Out | D34: 781400 | E34: Project Close Out-Geographic Information System | F34: M05 | G34: Close-out | H34: LBR | I34: 141 | J34: ='Optional - Sch & Resource Form'!C84 -> 0 | K34: Hr | L34: =I34*J34 -> 0
A35: M01 | B35: Engineering Standard | C35: =B35 & " - " & LEFT(E35,FIND("-",E35)-1) -> Engineering Standard - Capitalized Alloc Sup Svs | D35: 908550 | E35: Capitalized Alloc Sup Svs-Annual Engineering Adjustment | F35: M02 | G35: General Administration | I35: 63 | L35: =I35*J35 -> 0
A36: M01 | B36: Engineering Standard | C36: =B36 & " - " & LEFT(E36,FIND("-",E36)-1) -> Engineering Standard - Capitalized Alloc Sup Svs | D36: 909000 | E36: Capitalized Alloc Sup Svs-Capitalized Allocated Supp Svs | F36: M02 | G36: General Administration | I36: 63 | J36: ='Optional - Sch & Resource Form'!C87 -> 0 | K36: Hr | L36: =I36*J36 -> 0
A37: M02 | B37: IT Standard | C37: =B37 & " - " & LEFT(E37,FIND("-",E37)-1) -> IT Standard - Project Admin & Mgmt | D37: 101000 | E37: Project Admin & Mgmt-General | F37: M02 | G37: General Administration | H37: LBR | I37: 162 | K37: Hr | L37: =I37*J37 -> 0
A38: M02 | B38: IT Standard | C38: =B38 & " - " & LEFT(E38,FIND("-",E38)-1) -> IT Standard - Project Admin & Mgmt | D38: 101200 | E38: Project Admin & Mgmt-Project Mgmt | F38: M02 | G38: General Administration | H38: LBR | I38: 162 | K38: Hr | L38: =I38*J38 -> 0
A39: M02 | B39: IT Standard | C39: =B39 & " - " & LEFT(E39,FIND("-",E39)-1) -> IT Standard - Analysis & Requirements Defin. | D39: 121000 | E39: Analysis & Requirements Defin.-General | F39: M01 | G39: Project Planning | H39: LBR | I39: 149 | K39: Hr | L39: =I39*J39 -> 0
A40: M02 | B40: IT Standard | C40: =B40 & " - " & LEFT(E40,FIND("-",E40)-1) -> IT Standard - Analysis & Requirements Defin. | D40: 121200 | E40: Analysis & Requirements Defin.-Select Vendor | F40: M01 | G40: Project Planning | H40: LBR | I40: 149 | K40: Hr | L40: =I40*J40 -> 0
A41: M02 | B41: IT Standard | C41: =B41 & " - " & LEFT(E41,FIND("-",E41)-1) -> IT Standard - Security | D41: 131000 | E41: Security-General | F41: M02 | G41: General Administration | H41: LBR | I41: 149 | K41: Hr | L41: =I41*J41 -> 0
A42: M02 | B42: IT Standard | C42: =B42 & " - " & LEFT(E42,FIND("-",E42)-1) -> IT Standard - Design | D42: 141000 | E42: Design-General | F42: M03 | G42: Design | H42: LBR | I42: 149 | K42: Hr | L42: =I42*J42 -> 0
A43: M02 | B43: IT Standard | C43: =B43 & " - " & LEFT(E43,FIND("-",E43)-1) -> IT Standard - Design | D43: 141010 | E43: Design-Outside Design Services | F43: M03 | G43: Design | L43: =I43*J43 -> 0
A44: M02 | B44: IT Standard | C44: =B44 & " - " & LEFT(E44,FIND("-",E44)-1) -> IT Standard - Design | D44: 142600 | E44: Design-IT Design Support | F44: M03 | G44: Design | H44: LBR | I44: 149 | K44: Hr | L44: =I44*J44 -> 0
A45: M02 | B45: IT Standard | C45: =B45 & " - " & LEFT(E45,FIND("-",E45)-1) -> IT Standard - Acquisition | D45: 162300 | E45: Acquisition-Contract | F45: M04 | G45: Execute/Build | H45: LBR | I45: 149 | K45: Hr | L45: =I45*J45 -> 0
A46: M02 | B46: IT Standard | C46: =B46 & " - " & LEFT(E46,FIND("-",E46)-1) -> IT Standard - Acquisition | D46: 162400 | E46: Acquisition-Procurement | F46: M04 | G46: Execute/Build | H46: LBR | I46: 149 | K46: Hr | L46: =I46*J46 -> 0
A47: M02 | B47: IT Standard | C47: =B47 & " - " & LEFT(E47,FIND("-",E47)-1) -> IT Standard - Development | D47: 171000 | E47: Development-Database Administration | F47: M04 | G47: Execute/Build | H47: LBR | I47: 149 | K47: Hr | L47: =I47*J47 -> 0
A48: M02 | B48: IT Standard | C48: =B48 & " - " & LEFT(E48,FIND("-",E48)-1) -> IT Standard - Development | D48: 171100 | E48: Development-Software Develop. & Config. | F48: M04 | G48: Execute/Build | H48: LBR | I48: 149 | K48: Hr | L48: =I48*J48 -> 0
A49: M02 | B49: IT Standard | C49: =B49 & " - " & LEFT(E49,FIND("-",E49)-1) -> IT Standard - Development | D49: 171510 | E49: Development-Outside Design Services | F49: M04 | G49: Execute/Build | L49: =I49*J49 -> 0
A50: M02 | B50: IT Standard | C50: =B50 & " - " & LEFT(E50,FIND("-",E50)-1) -> IT Standard - Implementation | D50: 181400 | E50: Implementation-Hardware Installation | F50: M04 | G50: Execute/Build | H50: LBR | I50: 149 | K50: Hr | L50: =I50*J50 -> 0
A51: M02 | B51: IT Standard | C51: =B51 & " - " & LEFT(E51,FIND("-",E51)-1) -> IT Standard - Implementation | D51: 181600 | E51: Implementation-Software Installation | F51: M04 | G51: Execute/Build | H51: LBR | I51: 149 | K51: Hr | L51: =I51*J51 -> 0
A52: M02 | B52: IT Standard | C52: =B52 & " - " & LEFT(E52,FIND("-",E52)-1) -> IT Standard - Implementation | D52: 181700 | E52: Implementation-IT Conversion | F52: M04 | G52: Execute/Build | H52: LBR | I52: 149 | K52: Hr | L52: =I52*J52 -> 0
A53: M02 | B53: IT Standard | C53: =B53 & " - " & LEFT(E53,FIND("-",E53)-1) -> IT Standard - Construction | D53: 191810 | E53: Construction-Outside Construction Services | F53: M04 | G53: Execute/Build | L53: =I53*J53 -> 0
A54: M02 | B54: IT Standard | C54: =B54 & " - " & LEFT(E54,FIND("-",E54)-1) -> IT Standard - Documentation | D54: 261000 | E54: Documentation-Technical Documentation | F54: M04 | G54: Execute/Build | H54: LBR | I54: 149 | K54: Hr | L54: =I54*J54 -> 0
A55: M02 | B55: IT Standard | C55: =B55 & " - " & LEFT(E55,FIND("-",E55)-1) -> IT Standard - Documentation | D55: 261400 | E55: Documentation-Training Materials | F55: M04 | G55: Execute/Build | H55: LBR | I55: 149 | K55: Hr | L55: =I55*J55 -> 0
A56: M02 | B56: IT Standard | C56: =B56 & " - " & LEFT(E56,FIND("-",E56)-1) -> IT Standard - Testing | D56: 281000 | E56: Testing-General | F56: M04 | G56: Execute/Build | H56: LBR | I56: 149 | K56: Hr | L56: =I56*J56 -> 0
A57: M02 | B57: IT Standard | C57: =B57 & " - " & LEFT(E57,FIND("-",E57)-1) -> IT Standard - Training | D57: 291000 | E57: Training-Core User Training | F57: M04 | G57: Execute/Build | H57: LBR | I57: 149 | K57: Hr | L57: =I57*J57 -> 0
A58: M02 | B58: IT Standard | C58: =B58 & " - " & LEFT(E58,FIND("-",E58)-1) -> IT Standard - Training | D58: 291200 | E58: Training-Support Team Training | F58: M04 | G58: Execute/Build | H58: LBR | I58: 149 | K58: Hr | L58: =I58*J58 -> 0
A59: M02 | B59: IT Standard | C59: =B59 & " - " & LEFT(E59,FIND("-",E59)-1) -> IT Standard - Project Close Out | D59: 781000 | E59: Project Close Out-General | F59: M05 | G59: Close-out | H59: LBR | L59: =I59*J59 -> 0
A60: M02 | B60: IT Standard | C60: =B60 & " - " & LEFT(E60,FIND("-",E60)-1) -> IT Standard - Capitalized Alloc Sup Svs | D60: 908550 | E60: Capitalized Alloc Sup Svs-Annual Engineering Adjustment | F60: M02 | G60: General Administration | I60: 63 | L60: =I60*J60 -> 0
A61: M02 | B61: IT Standard | C61: =B61 & " - " & LEFT(E61,FIND("-",E61)-1) -> IT Standard - Capitalized Alloc Sup Svs | D61: 909000 | E61: Capitalized Alloc Sup Svs-Capitalized Allocated Supp Svs | F61: M02 | G61: General Administration | I61: 63 | L61: =I61*J61 -> 0
A62: M03 | B62: Upland Control Sites | C62: =B62 & " - " & LEFT(E62,FIND("-",E62)-1) -> Upland Control Sites - Project Admin & Mgmt | D62: 101000 | E62: Project Admin & Mgmt-General | F62: M02 | G62: General Administration | H62: LBR | L62: =I62*J62 -> 0
A63: M03 | B63: Upland Control Sites | C63: =B63 & " - " & LEFT(E63,FIND("-",E63)-1) -> Upland Control Sites - Design | D63: 141010 | E63: Design-Outside Design Services | F63: M03 | G63: Design | L63: =I63*J63 -> 0
A64: M03 | B64: Upland Control Sites | C64: =B64 & " - " & LEFT(E64,FIND("-",E64)-1) -> Upland Control Sites - Design | D64: 141400 | E64: Design-Remedial Design | F64: M03 | G64: Design | H64: LBR | L64: =I64*J64 -> 0
A65: M03 | B65: Upland Control Sites | C65: =B65 & " - " & LEFT(E65,FIND("-",E65)-1) -> Upland Control Sites - Design | D65: 141600 | E65: Design-Environmental | F65: M03 | G65: Design | H65: LBR | L65: =I65*J65 -> 0
A66: M03 | B66: Upland Control Sites | C66: =B66 & " - " & LEFT(E66,FIND("-",E66)-1) -> Upland Control Sites - Design | D66: 141700 | E66: Design-PE Design | F66: M03 | G66: Design | H66: LBR | L66: =I66*J66 -> 0
A67: M03 | B67: Upland Control Sites | C67: =B67 & " - " & LEFT(E67,FIND("-",E67)-1) -> Upland Control Sites - Design | D67: 142600 | E67: Design-IT Design Support | F67: M03 | G67: Design | H67: LBR | L67: =I67*J67 -> 0
A68: M03 | B68: Upland Control Sites | C68: =B68 & " - " & LEFT(E68,FIND("-",E68)-1) -> Upland Control Sites - Design | D68: 142700 | E68: Design-Maintenance Design Support | F68: M03 | G68: Design | H68: LBR | L68: =I68*J68 -> 0
A69: M03 | B69: Upland Control Sites | C69: =B69 & " - " & LEFT(E69,FIND("-",E69)-1) -> Upland Control Sites - Planning | D69: 151100 | E69: Planning-Assessment/Planning | F69: M03 | G69: Design | H69: LBR | L69: =I69*J69 -> 0
A70: M03 | B70: Upland Control Sites | C70: =B70 & " - " & LEFT(E70,FIND("-",E70)-1) -> Upland Control Sites - Planning | D70: 151110 | E70: Planning-Preliminary Assessment | F70: M03 | G70: Design | H70: LBR | L70: =I70*J70 -> 0
A71: M03 | B71: Upland Control Sites | C71: =B71 & " - " & LEFT(E71,FIND("-",E71)-1) -> Upland Control Sites - Planning | D71: 151200 | E71: Planning-Site Investigation | F71: M03 | G71: Design | H71: LBR | L71: =I71*J71 -> 0
A72: M03 | B72: Upland Control Sites | C72: =B72 & " - " & LEFT(E72,FIND("-",E72)-1) -> Upland Control Sites - Planning | D72: 151300 | E72: Planning-Remedial Investigation | F72: M03 | G72: Design | H72: LBR | L72: =I72*J72 -> 0
A73: M03 | B73: Upland Control Sites | C73: =B73 & " - " & LEFT(E73,FIND("-",E73)-1) -> Upland Control Sites - Planning | D73: 151310 | E73: Planning-Cargill OU1 | F73: M03 | G73: Design | H73: LBR | L73: =I73*J73 -> 0
A74: M03 | B74: Upland Control Sites | C74: =B74 & " - " & LEFT(E74,FIND("-",E74)-1) -> Upland Control Sites - Planning | D74: 151320 | E74: Planning-OU2 | F74: M03 | G74: Design | H74: LBR | L74: =I74*J74 -> 0
A75: M03 | B75: Upland Control Sites | C75: =B75 & " - " & LEFT(E75,FIND("-",E75)-1) -> Upland Control Sites - Planning | D75: 151600 | E75: Planning-Feasibility Study | F75: M03 | G75: Design | H75: LBR | L75: =I75*J75 -> 0
A76: M03 | B76: Upland Control Sites | C76: =B76 & " - " & LEFT(E76,FIND("-",E76)-1) -> Upland Control Sites - Development | D76: 171510 | E76: Development-Outside Design Services | F76: M04 | G76: Execute/Build | L76: =I76*J76 -> 0
A77: M03 | B77: Upland Control Sites | C77: =B77 & " - " & LEFT(E77,FIND("-",E77)-1) -> Upland Control Sites - Implementation | D77: 181000 | E77: Implementation-Remedial Action | F77: M04 | G77: Execute/Build | H77: LBR | L77: =I77*J77 -> 0
A78: M03 | B78: Upland Control Sites | C78: =B78 & " - " & LEFT(E78,FIND("-",E78)-1) -> Upland Control Sites - Implementation | D78: 181100 | E78: Implementation-O&M-Systems | F78: M04 | G78: Execute/Build | H78: LBR | L78: =I78*J78 -> 0
A79: M03 | B79: Upland Control Sites | C79: =B79 & " - " & LEFT(E79,FIND("-",E79)-1) -> Upland Control Sites - Implementation | D79: 181200 | E79: Implementation-O&M-Monitoring | F79: M04 | G79: Execute/Build | H79: LBR | L79: =I79*J79 -> 0
A80: M03 | B80: Upland Control Sites | C80: =B80 & " - " & LEFT(E80,FIND("-",E80)-1) -> Upland Control Sites - Construction | D80: 191810 | E80: Construction-Outside Construction Services | F80: M04 | G80: Execute/Build | L80: =I80*J80 -> 0
A81: M03 | B81: Upland Control Sites | C81: =B81 & " - " & LEFT(E81,FIND("-",E81)-1) -> Upland Control Sites - Legal/Regulatory | D81: 231300 | E81: Legal/Regulatory-Pre-Litigation Preparation | F81: M04 | G81: Execute/Build | H81: LBR | L81: =I81*J81 -> 0
A82: M03 | B82: Upland Control Sites | C82: =B82 & " - " & LEFT(E82,FIND("-",E82)-1) -> Upland Control Sites - Legal/Regulatory | D82: 231400 | E82: Legal/Regulatory-Litigation Defense | F82: M04 | G82: Execute/Build | H82: LBR | L82: =I82*J82 -> 0
A83: M03 | B83: Upland Control Sites | C83: =B83 & " - " & LEFT(E83,FIND("-",E83)-1) -> Upland Control Sites - Legal/Regulatory | D83: 231600 | E83: Legal/Regulatory-Closure Report/NFA | F83: M04 | G83: Execute/Build | H83: LBR | L83: =I83*J83 -> 0
A84: M03 | B84: Upland Control Sites | C84: =B84 & " - " & LEFT(E84,FIND("-",E84)-1) -> Upland Control Sites - Legal/Regulatory | D84: 231900 | E84: Legal/Regulatory-Action Memo | F84: M04 | G84: Execute/Build | H84: LBR | L84: =I84*J84 -> 0
A85: M03 | B85: Upland Control Sites | C85: =B85 & " - " & LEFT(E85,FIND("-",E85)-1) -> Upland Control Sites - Public Records Request | D85: 241000 | E85: Public Records Request-General | F85: M02 | G85: General Administration | H85: LBR | L85: =I85*J85 -> 0
A86: M03 | B86: Upland Control Sites | C86: =B86 & " - " & LEFT(E86,FIND("-",E86)-1) -> Upland Control Sites - Outreach | D86: 251000 | E86: Outreach-General | F86: M02 | G86: General Administration | H86: LBR | L86: =I86*J86 -> 0
A87: M03 | B87: Upland Control Sites | C87: =B87 & " - " & LEFT(E87,FIND("-",E87)-1) -> Upland Control Sites - Outreach | D87: 251010 | E87: Outreach-Community Relations | F87: M02 | G87: General Administration | H87: LBR | L87: =I87*J87 -> 0
A88: M03 | B88: Upland Control Sites | C88: =B88 & " - " & LEFT(E88,FIND("-",E88)-1) -> Upland Control Sites - Cost Recovery | D88: 301000 | E88: Cost Recovery-PRP Pursuit | F88: M04 | G88: Execute/Build | H88: LBR | L88: =I88*J88 -> 0
A89: M03 | B89: Upland Control Sites | C89: =B89 & " - " & LEFT(E89,FIND("-",E89)-1) -> Upland Control Sites - Payments | D89: 321000 | E89: Payments-Group Payments | F89: M04 | G89: Execute/Build | H89: LBR | L89: =I89*J89 -> 0
A90: M03 | B90: Upland Control Sites | C90: =B90 & " - " & LEFT(E90,FIND("-",E90)-1) -> Upland Control Sites - Payments | D90: 321300 | E90: Payments-Oversight Costs | F90: M04 | G90: Execute/Build | H90: LBR | L90: =I90*J90 -> 0
A91: M03 | B91: Upland Control Sites | C91: =B91 & " - " & LEFT(E91,FIND("-",E91)-1) -> Upland Control Sites - Payments | D91: 321310 | E91: Payments-Oversight Costs-EPA | F91: M04 | G91: Execute/Build | H91: LBR | L91: =I91*J91 -> 0
A92: M03 | B92: Upland Control Sites | C92: =B92 & " - " & LEFT(E92,FIND("-",E92)-1) -> Upland Control Sites - Payments | D92: 321320 | E92: Payments-Oversight Costs-DEQ | F92: M04 | G92: Execute/Build | H92: LBR | L92: =I92*J92 -> 0
... A94: M03 | B94: Upland Control Sites | C94: =B94 & " - " & LEFT(E94,FIND("-",E94)-1) -> Upland Control Sites - Payments | D94: 321340 | E94: Payments-Oversight Costs-Trustees | F94: M04 | G94: Execute/Build | H94: LBR | L94: =I94*J94 -> 0
A95: M03 | B95: Upland Control Sites | C95: =B95 & " - " & LEFT(E95,FIND("-",E95)-1) -> Upland Control Sites - Contingency | D95: 790000 | E95: Contingency-Contingency | F95: M02 | G95: General Administration | L95: =I95*J95 -> 0
A96: M03 | B96: Upland Control Sites | C96: =B96 & " - " & LEFT(E96,FIND("-",E96)-1) -> Upland Control Sites - Capitalized Alloc Sup Svs | D96: 909000 | E96: Capitalized Alloc Sup Svs-Capitalized Allocated Supp Svs | F96: M02 | G96: General Administration | L96: =I96*J96 -> 0
A97: M04 | B97: Natural Resource Damages | C97: =B97 & " - " & LEFT(E97,FIND("-",E97)-1) -> Natural Resource Damages - Project Admin & Mgmt | D97: 101000 | E97: Project Admin & Mgmt-General | F97: M02 | G97: General Administration | H97: LBR | L97: =I97*J97 -> 0
A98: M04 | B98: Natural Resource Damages | C98: =B98 & " - " & LEFT(E98,FIND("-",E98)-1) -> Natural Resource Damages - Design | D98: 141500 | E98: Design-Restoration | F98: M03 | G98: Design | H98: LBR | L98: =I98*J98 -> 0
A99: M04 | B99: Natural Resource Damages | C99: =B99 & " - " & LEFT(E99,FIND("-",E99)-1) -> Natural Resource Damages - Design | D99: 141510 | E99: Design-Restore. Plan & Dev, incl. Des | F99: M03 | G99: Design | H99: LBR | L99: =I99*J99 -> 0
A100: M04 | B100: Natural Resource Damages | C100: =B100 & " - " & LEFT(E100,FIND("-",E100)-1) -> Natural Resource Damages - Planning | D100: 151100 | E100: Planning-Assessment/Planning | F100: M03 | G100: Design | H100: LBR | L100: =I100*J100 -> 0
A101: M04 | B101: Natural Resource Damages | C101: =B101 & " - " & LEFT(E101,FIND("-",E101)-1) -> Natural Resource Damages - Planning | D101: 151120 | E101: Planning-Strategy/Planning | F101: M03 | G101: Design | H101: LBR | L101: =I101*J101 -> 0
A102: M04 | B102: Natural Resource Damages | C102: =B102 & " - " & LEFT(E102,FIND("-",E102)-1) -> Natural Resource Damages - Planning | D102: 151130 | E102: Planning-Injury Assessment | F102: M03 | G102: Design | H102: LBR | L102: =I102*J102 -> 0
...

Sheet Optional - Sch & Resource Form
A1: Schedule & Resource Estimate Form
A2: Project Title: | B2: =IF(Summary!B3<>"",Summary!B3,"")
A3: Project #: | B3: =IF(Summary!B4<>"",Summary!B4,"")
A4: Rev #: | B4: =IF(Summary!B9<>"",Summary!B9,"")
A5: Rev # Date: | B5: =IF(Summary!B8<>"",Summary!B8,"")
A7: Estimated Schedule
A8: Phase | B8: Start Date | C8: End Date | D8: Duration (Wks)
A9: Project Administration | D9: =IFERROR(DATEDIF(B9,C9,"d")/7,0) -> 0
A10: Design | D10: =IFERROR(DATEDIF(B10,C10,"d")/7,0) -> 0
A11: Execute/Build | D11: =IFERROR(DATEDIF(B11,C11,"d")/7,0) -> 0
A12: Close-Out | D12: =IFERROR(DATEDIF(B12,C12,"d")/7,0) -> 0
A14: Estimated Resources
A15: Role | B15: Avg. Hrs/Wk | C15: Total Hours
A16: Project Manager | C16: =B16*SUM($D$9:$D$12) -> 0
B17: TOTAL | C17: =C16 -> 0 | D17: 101000 - Project Admin & Mgmt-General
A19: Spec Writer | C19: =B19*$D$10 -> 0
B20: TOTAL | C20: =C19 -> 0 | D20: 141100 - Design-Specification Development
A22: Environmental Planner | C22: =B22*D10 -> 0
B23: TOTAL | C23: =C22 -> 0 | D23: 141600 - Design-Environmental
A25: Project Engineer | C25: =B25*$D$10 -> 0
A26: Electrical Engineer | C26: =B26*$D$10 -> 0
A27: Facility Engineer | C27: =B27*$D$10 -> 0
B28: TOTAL | C28: =SUM(C25:C27) -> 0 | D28: 141700 - Design-PE Design
A30: Surveyor | C30: =B30*$D$10 -> 0
A31: Locates | C31: =B31*$D$10 -> 0
B32: TOTAL | C32: =SUM(C30:C31) -> 0 | D32: 141800 - Design-Survey
A34: CAD Tech | C34: =B34*$D$10 -> 0
A35: BIM Tech | C35: =B35*$D$10 -> 0
A36: TRC Tech | C36: =B36*$D$10 -> 0
B37: TOTAL | C37: =SUM(C34:C36) -> 0 | D37: 141900 - Design-Drawing and Development
A39: Construction Manager | C39: =B39*$D$10 -> 0
A40: Inspector | C40: =B40*$D$10 -> 0
B41: TOTAL | C41: =SUM(C39:C40) -> 0 | D41: 142100 - Design-Construction/Inspection Support
A43: IT Resource | C43: =B43*$D$10 -> 0
B44: TOTAL | C44: =C43 -> 0 | D44: 142600 - Design-IT Design Support
A46: Construction Manager | C46: =B46*$D$11 -> 0
B47: TOTAL | C47: =C46 -> 0 | D47: 191200 - Construction-Management
A49: Civil Inspector | C49: =B49*$D$11 -> 0
A50: Electrical Inspector | C50: =B50*$D$11 -> 0
A51: Mechanical Inspector | C51: =B51*$D$11 -> 0
B52: TOTAL | C52: =SUM(C49:C51) -> 0 | D52: 191300 - Construction-Inspection
A54: Surveyor | C54: =B54*$D$11 -> 0
A55: Locates | C55: =B55*$D$11 -> 0
B56: TOTAL | C56: =SUM(C54:C55) -> 0 | D56: 191500 - Construction-Survey
A58: Environmental Specialist | C58: =B58*$D$11 -> 0
B59: TOTAL | C59: =C58 -> 0 | D59: 191600 - Construction-Environmental
A61: Project Engineer | C61: =B61*$D$11 -> 0
A62: Electrical Engineer | C62: =B62*$D$11 -> 0
A63: Facility Engineer | C63: =B63*$D$11 -> 0
B64: TOTAL | C64: =SUM(C61:C63) -> 0 | D64: 191800 - Construction-Engineering Support
A66: Maintenance Personnel | C66: =B66*D11 -> 0
B67: TOTAL | C67: =C66 -> 0 | D67: 191900 - Construction-Maintenance
A69: IT Resource | C69: =B69*D11 -> 0
B70: TOTAL | C70: =C69 -> 0 | D70: 192000 - Construction-IT
A72: Project Engineer | C72: =B72*$D$12 -> 0
A73: CAD Tech | C73: =B73*$D$12 -> 0
A74: BIM Tech | C74: =B74*$D$12 -> 0
B75: TOTAL | C75: =SUM(C72:C74) -> 0 | D75: 781100 - Project Close Out-As Builts
A77: Surveyor | C77: =B77*D12 -> 0
B78: TOTAL | C78: =C77 -> 0 | D78: 781200 - Project Close Out-Survey
A80: TRC Tech | C80: =B80*$D$12 -> 0
B81: TOTAL | C81: =C80 -> 0 | D81: 781300 - Project Close Out-Technical Reference Center
A83: GIS Analyst | C83: =B83*$D$12 -> 0
B84: TOTAL | C84: =C83 -> 0 | D84: 781400 - Project Close Out-Geographic Information System
A86: CASS | C86: =C17+C20+C28+C32+C37+C41+C44+C47+C52+C56+C64+C70+C75+C78+C81+C84 -> 0
B87: TOTAL | C87: =C86 -> 0 | D87: 909000 - Capitalized Alloc Sup Svs-Capitalized Allocated Supp Svs
B89: Total Hours | C89: =C87+C84+C81+C78+C75+C70+C67+C64+C59+C56+C52+C47+C44+C41+C37+C32+C28+C23+C20+C17 -> 0

Sheet Dashboard
B3: ESTIMATE DASHBOARD
B6: Project Title: | E6: =IF(Summary!B3<>"",Summary!B3,"")
B7: Project #: | E7: =IF(Summary!B4<>"",Summary!B4,"")
B8: Rev # | E8: =IF(Summary!B9<>"",Summary!B9,"")
B9: Rev # Date | E9: =IF(Summary!B8<>"",Summary!B8,"")
B12: Project Estimate Chart
B36: Chart is auto-populated from 'Project Estimate' table below
B38: Project Estimate
B39: Risk = Contingency + Escalation | I39: Performance Metric
D40: Hard ($) | E40: Soft ($) | F40: Contingency ($) | G40: Escalation ($) | H40: Estimate ($) | I40: Low Range ($) | J40: High Range ($)
B41: Project Charter
B42: Business Case - Gate 1
B43: Preliminary Design - Gate 2
B44: 100% Design/ Pre-Bid - Gate 3
B45: Bid Acceptance - Gate 4
B46: Project Closeout - Gate 5

Sheet DivisionCostCodeLookup
A1: Division | B1: CostCode | C1: Division Number | D1: DivisionLookup | F1: Description | G1: CostCode | H1: Division Number | I1: CostCodeSeg 2 | J1: CostCodeSeg 3 | L1: Description | M1: Costcode | P1: SUBGROUP: GENERAL REQUIREMENTS
A2: 01 General Requirements | B2: 10000 | C2: 1 | D2: Division01 | G2: 10000 | H2: 1 | I2: 00 | J2: 00 | L2: PROJECT MANAGEMENT | M2: 100000 | P2: Division 01 - General Requirements
A3: 02 Existing Conditions | B3: 20000 | C3: 2 | D3: Division02 | F3: Contractor'sManagementandCoordination | G3: 13100 | H3: 1 | I3: 31 | J3: 00 | L3: DESIGN | M3: 140000 | P3: 13100 | Q3: Contractor's Management and Coordination
A4: 03 Concrete | B4: 30000 | C4: 3 | D4: Division03 | F4: SubmittalProcedures | G4: 13300 | H4: 1 | I4: 33 | J4: 0 | L4: DEVELOPMENT | M4: 170000 | P4: 13300 | Q4: Submittal Procedures
A5: 04 Masonry | B5: 40000 | C5: 4 | D5: Division04 | F5: SecurityControl | G5: 13500 | H5: 1 | I5: 35 | J5: 0 | L5: CONSTRUCTION | M5: 190000 | P5: 13500 | Q5: Security Control
A6: 05 Metals | B6: 50000 | C6: 5 | D6: Division05 | F6: Escort | G6: 13501 | H6: 1 | I6: 35 | J6: 1 | L6: PERMITTING | M6: 200000 | P6: 13501 | Q6: Escort
A7: 06 Wood Plastics And Composites | B7: 60000 | C7: 6 | D7: Division06 | F7: Permits | G7: 14100 | H7: 1 | I7: 14 | J7: 0 | P7: 14100 | Q7: Permits
A8: 07 Thermaland Moisture Protection | B8: 70000 | C8: 7 | D8: Division07 | F8: MobilizationandDemobilization | G8: 15000 | H8: 1 | I8: 50 | J8: 00 | L8: PROJECT CLOSE-OUT | M8: 780000 | P8: 15000 | Q8: Mobilization and Demobilization
A9: 08 Openings | B9: 80000 | C9: 8 | D9: Division08 | F9: TrafficControl | G9: 15001 | H9: 1 | I9: 50 | J9: 1 | L9: CONTINGENCY | M9: 790000 | P9: 15001 | Q9: Traffic Control
A10: 09 Finishes | B10: 90000 | C10: 9 | D10: Division09 | F10: Sweeping | G10: 15002 | H10: 1 | I10: 50 | J10: 2 | L10: CASS | M10: 909000 | P10: 15002 | Q10: Sweeping
A11: 10 Specialties | B11: 100000 | C11: 10 | D11: Division10 | F11: TemporaryHeating,CoolingandVentilating | G11: 15123 | H11: 1 | I11: 51 | J11: 23 | L11: CONVERSION | M11: 0 | P11: 15123 | Q11: Temporary Heating, Cooling and Ventilating
A12: 11 Equipment | B12: 110000 | C12: 11 | D12: Division11 | F12: TemporaryRamps | G12: 15323 | H12: 1 | I12: 53 | J12: 23 | P12: 15323 | Q12: Temporary Ramps
A13: 12 Furnishings | B13: 120000 | C13: 12 | D13: Division12 | F13: ConstructionAids | G13: 15400 | H13: 1 | I13: 54 | J13: 0 | P13: 15400 | Q13: Construction Aids
A14: 13 Special Construction | B14: 130000 | C14: 13 | D14: Division13 | F14: VehicularAccessandParking | G14: 15500 | H14: 1 | I14: 55 | J14: 0 | P14: 15500 | Q14: Vehicular Access and Parking
A15: 14 Conveying Equipment | B15: 140000 | C15: 14 | D15: Division14 | F15: TemporaryBarriersandEnclosures | G15: 15600 | H15: 1 | I15: 56 | J15: 0 | P15: 15600 | Q15: Temporary Barriers and Enclosures
A16: 21 Fire Suppression | B16: 210000 | C16: 21 | D16: Division21 | F16: TemporaryErosion,Sediment,andPollutionControl | G16: 15713 | H16: 1 | I16: 57 | J16: 13 | P16: 15713 | Q16: Temporary Erosion, Sediment, and Pollution Control
A17: 22 Plumbing | B17: 220000 | C17: 22 | D17: Division22 | F17: ProductStorageandHandlingRequirements | G17: 16600 | H17: 1 | I17: 66 | J17: 0 | P17: 16600 | Q17: Product Storage and Handling Requirements
A18: 23 Heating Ventilating And Air Conditioning | B18: 230000 | C18: 23 | D18: Division23 | F18: CuttingandPatching | G18: 17329 | H18: 1 | I18: 73 | J18: 29 | P18: 17329 | Q18: Cutting and Patching
A19: 26 Electrical | B19: 260000 | C19: 26 | D19: Division26 | F19: CleaningandWasteManagement | G19: 17400 | H19: 1 | I19: 74 | J19: 00 | P19: 17400 | Q19: Cleaning and Waste Management
A20: 27 Communications | B20: 270000 | C20: 27 | D20: Division27 | F20: ConstructionWasteRecycling | G20: 17419 | H20: 1 | I20: 74 | J20: 19 | P20: 17419 | Q20: Construction Waste Recycling
A21: 28 Electronic Safety And Security | B21: 280000 | C21: 28 | D21: Division28 | F21: Commissioning | G21: 19100 | H21: 1 | I21: 91 | J21: 0 | P21: 19100 | Q21: Commissioning
A22: 31 Earthwork | B22: 310000 | C22: 31 | D22: Division31 | P22: SUBGROUP: FACILITY CONSTRUCTION
A23: 32 Exterior Improvements | B23: 320000 | C23: 32 | D23: Division32 | G23: 20000 | H23: 2 | I23: 00 | J23: 00 | P23: Division 02 - Existing Conditions
A24: 33 Utilities | B24: 330000 | C24: 33 | D24: Divsion33 | F24: CommonWorkResultsforExistingConditions | G24: 20500 | H24: 2 | I24: 05 | J24: 00 | P24: 20500 | Q24: Common Work Results for Existing Conditions
A25: 34 Transportation | B25: 340000 | C25: 34 | D25: Division34 | F25: SiteDemolition | G25: 24113 | H25: 2 | I25: 41 | J25: 13 | P25: 24113 | Q25: Site Demolition
A26: 35 Waterway And Marine | B26: 350000 | C26: 35 | D26: Division35 | F26: SelectiveInteriorDemolition | G26: 24119 | H26: 2 | I26: 41 | J26: 19 | P26: 24119 | Q26: Selective Interior Demolition
A27: 41 Material Proc And Handling Eq. | B27: 410000 | C27: 41 | D27: Divsion41 | F27: SiteRemediation | G27: 25000 | H27: 2 | I27: 50 | J27: 00 | P27: 25000 | Q27: Site Remediation
A28: 51 Earthwork FAA | B28: 510000 | C28: 51 | D28: Division51 | F28: RemovalandDisposalofContaminatedSoils | G28: 26100 | H28: 2 | I28: 61 | J28: 00 | P28: 26100 | Q28: Removal and Disposal of Contaminated Soils
A29: 52 Flexible Base Courses FAA | B29: 520000 | C29: 52 | D29: Division52 | F29: UndergroundStorageTankRemoval | G29: 26500 | H29: 2 | I29: 65 | J29: 00 | P29: 26500 | Q29: Underground Storage Tank Removal
A30: 53 Rigid Base Courses FAA | B30: 530000 | C30: 53 | D30: Division53 | F30: GroundwaterTreatment | G30: 27100 | H30: 2 | I30: 71 | J30: 0 | P30: 27100 | Q30: Groundwater Treatment
A31: 54 Flexible Surface Courses FAA | B31: 540000 | C31: 54 | D31: Division54 | F31: AsbestosAbatement | G31: 28213 | H31: 2 | I31: 82 | J31: 13 | P31: 28213 | Q31: Asbestos Abatement
A32: 55 Rigid Pavement FAA | B32: 550000 | C32: 55 | D32: Division55 | F32: AsbestosManagement | G32: 28216 | H32: 2 | I32: 82 | J32: 16 | P32: 28216 | Q32: Asbestos Management
A33: 56 Miscellaneous FAA | B33: 560000 | C33: 56 | D33: Division56 | F33: Lead_BasedPaintManagement | G33: 28313 | H33: 2 | I33: 83 | J33: 13 | P33: 28313 | Q33: Lead-Based Paint Management
A34: 57 Fencing FAA | B34: 570000 | C34: 57 | D34: Division57 | F34: Lead_BasedPaintAbatement | G34: 28319 | H34: 2 | I34: 83 | J34: 19 | P34: 28319 | Q34: Lead-Based Paint Abatement
A35: 58 Drainage FAA | B35: 580000 | C35: 58 | D35: Division58 | F35: PCBRemediation | G35: 28400 | H35: 2 | I35: 84 | J35: 00 | P35: 28400 | Q35: PCB Remediation
A36: 59 Turfing FAA | B36: 590000 | C36: 59 | D36: Division59
A37: 60 Lighting Installation FAA | B37: 600000 | C37: 60 | D37: Division60 | G37: 30000 | H37: 3 | I37: 00 | J37: 00 | P37: Division 03 - Concrete
F38: CommonWorkResultsforConcrete | G38: 30500 | H38: 3 | I38: 05 | J38: 00 | P38: 30500 | Q38: Common Work Results for Concrete
F39: ConcreteFormwork | G39: 31100 | H39: 3 | I39: 11 | J39: 00 | P39: 31100 | Q39: Concrete Formwork
F40: ConcreteAccessories | G40: 31500 | H40: 3 | I40: 15 | J40: 00 | P40: 31500 | Q40: Concrete Accessories
F41: ConcreteReinforcing | G41: 32000 | H41: 3 | I41: 20 | J41: 00 | P41: 32000 | Q41: Concrete Reinforcing
F42: Cast_In_PlaceConcrete | G42: 33000 | H42: 3 | I42: 30 | J42: 00 | P42: 33000 | Q42: Cast-In-Place Concrete
F43: ConcreteGrouting | G43: 36000 | H43: 3 | I43: 60 | J43: 00 | P43: 36000 | Q43: Concrete Grouting
G45: 40000 | H45: 4 | I45: 00 | J45: 00 | P45: Division 04 - Masonry
F46: CommonWorkResultsforMasonry | G46: 40500 | H46: 4 | I46: 05 | J46: 00 | P46: 40500 | Q46: Common Work Results for Masonry
F47: MasonryMortarandGrout | G47: 40513 | H47: 4 | I47: 05 | J47: 13 | P47: 40513 | Q47: Masonry Mortar and Grout
F48: MasonryAccessories | G48: 40523 | H48: 4 | I48: 05 | J48: 23 | P48: 40523 | Q48: Masonry Accessories
F49: BrickMasonry | G49: 42113 | H49: 4 | I49: 21 | J49: 13 | P49: 42113 | Q49: Brick Masonry
F50: ConcreteUnitMasonry | G50: 42200 | H50: 4 | I50: 22 | J50: 00 | P50: 42200 | Q50: Concrete Unit Masonry
G52: 50000 | H52: 5 | I52: 00 | J52: 00 | P52: Division 05 - Metals
F53: CommonWorkResultsforMetals | G53: 50500 | H53: 5 | I53: 05 | J53: 00 | P53: 50500 | Q53: Common Work Results for Metals
F54: GalvanicCoatings | G54: 50513 | H54: 5 | I54: 05 | J54: 13 | P54: 50513 | Q54: Galvanic Coatings
F55: StructuralSteelFraming | G55: 51200 | H55: 5 | I55: 12 | J55: 00 | P55: 51200 | Q55: Structural Steel Framing
F56: ArchitecturallyExposedStructuralSteelFraming | G56: 51213 | H56: 5 | I56: 12 | J56: 13 | P56: 51213 | Q56: Architecturally Exposed Structural Steel Framing
F57: SteelJoistFraming | G57: 52100 | H57: 5 | I57: 21 | J57: 00 | P57: 52100 | Q57: Steel Joist Framing
F58: SteelDecking | G58: 53100 | H58: 5 | I58: 31 | J58: 00 | P58: 53100 | Q58: Steel Decking
F59: Cold_FormedMetalFraming | G59: 54000 | H59: 5 | I59: 40 | J59: 00 | P59: 54000 | Q59: Cold-Formed Metal Framing
F60: MetalFabrications | G60: 55000 | H60: 5 | I60: 50 | J60: 00 | P60: 55000 | Q60: Metal Fabrications
F61: MetalRailings | G61: 55200 | H61: 5 | I61: 52 | J61: 00 | P61: 55200 | Q61: Metal Railings
F62: StainlessSteelFabrications | G62: 57050 | H62: 5 | I62: 70 | J62: 50 | P62: 57050 | Q62: Stainless Steel Fabrications
F63: GlazedDecorativeMetalRailings | G63: 57300 | H63: 5 | I63: 73 | J63: 00 | P63: 57300 | Q63: Glazed Decorative Metal Railings
F64: DecorativeFormedMetal | G64: 57500 | H64: 5 | I64: 75 | J64: 00 | P64: 57500 | Q64: Decorative Formed Metal
G66: 60000 | H66: 6 | I66: 00 | J66: 00 | P66: Division 06 - Wood, Plastics & Composites
F67: CommonWorkResultsforWood.Plastics&Composites | G67: 60500 | H67: 6 | I67: 05 | J67: 00 | P67: 60500 | Q67: Common Work Results for Wood, Plastics & Composites
F68: MaintenanceofWood.Plastics.andComposites | G68: 60100 | H68: 6 | I68: 01 | J68: 00 | P68: 60100 | Q68: Maintenance of Wood, Plastics, and Composites
F69: RoughCarpentry | G69: 61000 | H69: 6 | I69: 10 | J69: 00 | P69: 61000 | Q69: Rough Carpentry
F70: FramingandSheathing | G70: 61100 | H70: 6 | I70: 11 | J70: 00 | P70: 61100 | Q70: Framing and Sheathing
F71: TreatedWoodforRoofRepairs | G71: 61400 | H71: 6 | I71: 14 | J71: 00 | P71: 61400 | Q71: Treated Wood for Roof Repairs
F72: FinishCarpentry | G72: 62000 | H72: 6 | I72: 20 | J72: 00 | P72: 62000 | Q72: Finish Carpentry
F73: ArchitecturalWoodwork | G73: 64000 | H73: 6 | I73: 40 | J73: 00 | P73: 64000 | Q73: Architectural Woodwork
F74: CustomCabinets | G74: 64100 | H74: 6 | I74: 41 | J74: 00 | P74: 64100 | Q74: Custom Cabinets
F75: WoodPaneling | G75: 64200 | H75: 6 | I75: 42 | J75: 00 | P75: 64200 | Q75: Wood Paneling
F76: CustomCasework | G76: 64600 | H76: 6 | I76: 46 | J76: 00 | P76: 64600 | Q76: Custom Casework
F77: PlasticStructuralLumber | G77: 65113 | H77: 6 | I77: 51 | J77: 13 | P77: 65113 | Q77: Plastic Structural Lumber
F78: PlasticFabrications | G78: 66000 | H78: 6 | I78: 60 | J78: 00 | P78: 66000 | Q78: Plastic Fabrications
G80: 70000 | H80: 7 | I80: 00 | J80: 00 | P80: Division 07 - Thermal and Moisture Protection
F81: CommonWorkResultsforThermalandMoistureProtection | G81: 70500 | H81: 7 | I81: 05 | J81: 00 | P81: 70500 | Q81: Common Work Results for Thermal and Moisture Protection
F82: ModifiedBituminousSheetRoofingSystemRepairs | G82: 70152 | H82: 7 | I82: 01 | J82: 52 | P82: 70152 | Q82: Modified Bituminous Sheet Roofing System Repairs
F83: ElastomericSheetRoofingSystemRepairs | G83: 70153 | H83: 7 | I83: 01 | J83: 53 | P83: 70153 | Q83: Elastomeric Sheet Roofing System Repairs
F84: Waterproofing | G84: 71000 | H84: 7 | I84: 10 | J84: 00 | P84: 71000 | Q84: Waterproofing
F85: Dampproofing | G85: 71100 | H85: 7 | I85: 11 | J85: 00 | P85: 71100 | Q85: Damp proofing
F86: TrafficCoatings | G86: 71800 | H86: 7 | I86: 18 | J86: 00 | P86: 71800 | Q86: Traffic Coatings
F87: ThermalInsulation | G87: 72100 | H87: 7 | I87: 21 | J87: 00 | P87: 72100 | Q87: Thermal Insulation
F88: VaporRetarders | G88: 72600 | H88: 7 | I88: 26 | J88: 00 | P88: 72600 | Q88: Vapor Retarders
F89: AirBarriers | G89: 72700 | H89: 7 | I89: 27 | J89: 00 | P89: 72700 | Q89: Air Barriers
F90: RoofPanels | G90: 74100 | H90: 7 | I90: 41 | J90: 00 | P90: 74100 | Q90: Roof Panels
F91: WallPanels | G91: 74200 | H91: 7 | I91: 42 | J91: 00 | P91: 74200 | Q91: Wall Panels
F92: MembraneRoofing | G92: 75000 | H92: 7 | I92: 50 | J92: 00 | P92: 75000 | Q92: Membrane Roofing
F93: Built_UpBituminousRoofing | G93: 75100 | H93: 7 | I93: 51 | J93: 00 | P93: 75100 | Q93: Built-Up Bituminous Roofing
... F103: ExpansionControl | G103: 79500 | H103: 7 | I103: 95 | J103: 00 | P103: 79500 | Q103: Expansion Control
G105: 80000 | H105: 8 | I105: 00 | J105: 00 | P105: Division 08 - Openings
F106: CommonWorkResultsforOpenings | G106: 80500 | H106: 8 | I106: 05 | J106: 00 | P106: 80500 | Q106: Common Work Results for Openings
F107: Door/WindowSchedule | G107: 80600 | H107: 8 | I107: 06 | J107: 00 | P107: 80600 | Q107: Door/Window Schedule
F108: MetalDoorsandFrames | G108: 81100 | H108: 8 | I108: 11 | J108: 00 | P108: 81100 | Q108: Metal Doors and Frames
F109: WoodDoors | G109: 81400 | H109: 8 | I109: 14 | J109: 00 | P109: 81400 | Q109: Wood Doors
F110: AccessDoorsandPanels | G110: 83100 | H110: 8 | I110: 31 | J110: 00 | P110: 83100 | Q110: Access Doors and Panels
F111: CoilingDoorsandGrilles | G111: 83300 | H111: 8 | I111: 33 | J111: 00 | P111: 83300 | Q111: Coiling Doors and Grilles
F112: PanelDoors | G112: 83600 | H112: 8 | I112: 36 | J112: 00 | P112: 83600 | Q112: Panel Doors
F113: AluminumEntrancesandStorefronts | G113: 84113 | H113: 8 | I113: 41 | J113: 13 | P113: 84113 | Q113: Aluminum Entrances and Storefronts
F114: All_GlassEntrancesandStorefronts | G114: 84126 | H114: 8 | I114: 41 | J114: 26 | P114: 84126 | Q114: All-Glass Entrances and Storefronts
...

Sheet Soft Cost Codes
A1: Shrt | B1: Division | C1: Description | D1: Lookup | E1: SubType | F1: Cost Code | G1: Seg1 | H1: Seg2 | I1: Seg3 | K1: SubType | L1: Cost Code | M1: Seg1 | N1: Seg2 | O1: Seg3
A2: SIT | B2: Division 1 | C2: Channel_Deepening_Site_Channel_Deepening | D2: Channel_Deepening_Site_Channel_Deepening_Acquisition | E2: Acquisition | F2: 160000 | G2: 16 | H2: 0 | I2: 0 | K2: ProjectAdminMgmt | L2: 100000 | M2: 10 | N2: 0 | O2: 0
A3: SIT | B3: Division 1 | C3: Channel_Deepening_Site_Channel_Deepening | E3: General | F3: 161000 | G3: 16 | H3: 10 | I3: 0 | K3: General | L3: 101000 | M3: 10 | N3: 10 | O3: 0
A4: SIT | B4: Division 1 | C4: Channel_Deepening_Site_Channel_Deepening | E4: Demolition | F4: 161200 | G4: 16 | H4: 12 | I4: 0 | K4: ProjectAdminandMgmt | L4: 100000 | M4: 10 | N4: 0 | O4: 0
A5: SIT | B5: Division 1 | C5: Channel_Deepening_Site_Channel_Deepening | E5: RelocationAssistance | F5: 161300 | G5: 16 | H5: 13 | I5: 0 | K5: LandAcquisition | L5: 101600 | M5: 10 | N5: 16 | O5: 0
A6: SIT | B6: Division 1 | C6: Channel_Deepening_Site_Channel_Deepening | E6: Appraisals | F6: 161400 | G6: 16 | H6: 14 | I6: 0 | K6: FinancialSupport | L6: 101700 | M6: 10 | N6: 17 | O6: 0
A7: SIT | B7: Division 1 | C7: Channel_Deepening_Site_Channel_Deepening | E7: EnvironmentalAssessments | F7: 161500 | G7: 16 | H7: 15 | I7: 0 | K7: LegislativeFunding | L7: 101800 | M7: 10 | N7: 18 | O7: 0
A8: SIT | B8: Division 1 | C8: Channel_Deepening_Site_Channel_Deepening | E8: Condemnation | F8: 161600 | G8: 16 | H8: 16 | I8: 0 | K8: Agreements | L8: 101900 | M8: 10 | N8: 19 | O8: 0
A9: SIT | B9: Division 1 | C9: Channel_Deepening_Site_Channel_Deepening | E9: Inspection | F9: 161700 | G9: 16 | H9: 17 | I9: 0 | K9: ProjectMgmt | L9: 101200 | M9: 10 | N9: 12 | O9: 0
A10: SIT | B10: Division 1 | C10: Channel_Deepening_Site_Channel_Deepening | E10: TitleWork | F10: 161800 | G10: 16 | H10: 18 | I10: 0 | K10: UplandSourceControlProgramCoordination | L10: 101010 | M10: 10 | N10: 10 | O10: 10
A11: SIT | B11: Division 1 | C11: Channel_Deepening_Site_Channel_Deepening | E11: Survey | F11: 162200 | G11: 16 | H11: 22 | I11: 0 | K11: ProgramManagement | L11: 101020 | M11: 10 | N11: 10 | O11: 20
A12: SIT | B12: Division 1 | C12: Channel_Deepening_Site_Channel_Deepening | D12: Channel_Deepening_Site_Channel_Deepening_Permitting | E12: Permitting | F12: 200000 | G12: 20 | H12: 0 | I12: 0 | K12: Meetings | L12: 101100 | M12: 10 | N12: 11 | O12: 0
A13: SIT | B13: Division 1 | C13: Channel_Deepening_Site_Channel_Deepening | E13: General | F13: 201000 | G13: 20 | H13: 10 | I13: 0 | K13: Development | L13: 101300 | M13: 10 | N13: 13 | O13: 0
A14: SIT | B14: Division 1 | C14: Channel_Deepening_Site_Channel_Deepening | D14: Channel_Deepening_Site_Channel_Deepening_Contingency | E14: Contingency | F14: 790000 | G14: 79 | H14: 0 | I14: 0 | K14: Design | L14: 101400 | M14: 10 | N14: 14 | O14: 0
A15: UPL | B15: Division 1 | C15: Upland_Control_Sites_Lower_Willamette | D15: Upland_Control_Sites_Lower_Willamette_ProjectAdminMgmt | E15: ProjectAdminMgmt | F15: 100000 | G15: 10 | H15: 0 | I15: 0 | K15: Construction | L15: 101500 | M15: 10 | N15: 15 | O15: 0
A16: UPL | B16: Division 1 | C16: Upland_Control_Sites_Lower_Willamette | E16: General | F16: 101000 | G16: 10 | H16: 10 | I16: 0 | K16: Develop | L16: 101300 | M16: 10 | N16: 13 | O16: 0
A17: UPL | B17: Division 1 | C17: Upland_Control_Sites_Lower_Willamette | D17: Upland_Control_Sites_Lower_Willamette_Design | E17: Design | F17: 140000 | G17: 14 | H17: 0 | I17: 0 | K17: BusinessContinuity | L17: 110000 | M17: 11 | N17: 0 | O17: 0
A18: UPL | B18: Division 1 | C18: Upland_Control_Sites_Lower_Willamette | E18: OutsideDesignServices | F18: 141010 | G18: 14 | H18: 10 | I18: 10 | K18: General | L18: 111000 | M18: 11 | N18: 10 | O18: 0
A19: UPL | B19: Division 1 | C19: Upland_Control_Sites_Lower_Willamette | E19: TreatabilityStudy_PilotTesting | F19: 141300 | G19: 14 | H19: 13 | I19: 0 | K19: AnalysisandRequirementsDefinition | L19: 120000 | M19: 12 | N19: 0 | O19: 0
A20: UPL | B20: Division 1 | C20: Upland_Control_Sites_Lower_Willamette | E20: RemedialDesign | F20: 141400 | G20: 14 | H20: 14 | I20: 0 | K20: General | L20: 121000 | M20: 12 | N20: 10 | O20: 0
A21: UPL | B21: Division 1 | C21: Upland_Control_Sites_Lower_Willamette | E21: Enviornmental | F21: 141600 | G21: 14 | H21: 16 | I21: 0 | K21: DevelopandIssueRFP | L21: 121100 | M21: 12 | N21: 11 | O21: 0
A22: UPL | B22: Division 1 | C22: Upland_Control_Sites_Lower_Willamette | E22: PEDesign | F22: 141700 | G22: 14 | H22: 17 | I22: 0 | K22: SelectVendor | L22: 121200 | M22: 12 | N22: 12 | O22: 0
A23: UPL | B23: Division 1 | C23: Upland_Control_Sites_Lower_Willamette | E23: ITDesignSupport | F23: 142600 | G23: 14 | H23: 26 | I23: 0 | K23: Security | L23: 130000 | M23: 13 | N23: 0 | O23: 0
A24: UPL | B24: Division 1 | C24: Upland_Control_Sites_Lower_Willamette | E24: MaintenanceDesignSupport | F24: 142700 | G24: 14 | H24: 27 | I24: 0 | K24: General | L24: 131000 | M24: 13 | N24: 10 | O24: 0
A25: UPL | B25: Division 1 | C25: Upland_Control_Sites_Lower_Willamette | D25: Upland_Control_Sites_Lower_Willamette_Planning | E25: Planning | F25: 150000 | G25: 15 | H25: 0 | I25: 0 | K25: Design | L25: 140000 | M25: 14 | N25: 0 | O25: 0
A26: UPL | B26: Division 1 | C26: Upland_Control_Sites_Lower_Willamette | E26: AssessmentPlanning | F26: 151100 | G26: 15 | H26: 11 | I26: 0 | K26: OutsideDesignServices | L26: 141010 | M26: 14 | N26: 10 | O26: 10
A27: UPL | B27: Division 1 | C27: Upland_Control_Sites_Lower_Willamette | E27: PreliminaryAssessment | F27: 151110 | G27: 15 | H27: 11 | I27: 10 | K27: TreatabilityStudy_PilotTesting | L27: 141300 | M27: 14 | N27: 13 | O27: 0
A28: UPL | B28: Division 1 | C28: Upland_Control_Sites_Lower_Willamette | E28: SiteInvestigation | F28: 151200 | G28: 15 | H28: 12 | I28: 0 | K28: RemedialDesign | L28: 141400 | M28: 14 | N28: 14 | O28: 0
A29: UPL | B29: Division 1 | C29: Upland_Control_Sites_Lower_Willamette | E29: RemedialInvestigation | F29: 151300 | G29: 15 | H29: 13 | I29: 0 | K29: Enviornmental | L29: 141600 | M29: 14 | N29: 16 | O29: 0
A30: UPL | B30: Division 1 | C30: Upland_Control_Sites_Lower_Willamette | E30: CargillOU1 | F30: 151310 | G30: 15 | H30: 13 | I30: 10 | K30: PEDesign | L30: 141700 | M30: 14 | N30: 17 | O30: 0
A31: UPL | B31: Division 1 | C31: Upland_Control_Sites_Lower_Willamette | E31: OU2 | F31: 151320 | G31: 15 | H31: 13 | I31: 20 | K31: ITDesignSupport | L31: 142600 | M31: 14 | N31: 26 | O31: 0
A32: UPL | B32: Division 1 | C32: Upland_Control_Sites_Lower_Willamette | E32: FeasibilityStudy | F32: 151600 | G32: 15 | H32: 16 | I32: 0 | K32: MaintenanceDesignSupport | L32: 142700 | M32: 14 | N32: 27 | O32: 0
A33: UPL | B33: Division 1 | C33: Upland_Control_Sites_Lower_Willamette | E33: CulturalResources | F33: 151700 | G33: 15 | H33: 17 | I33: 0 | K33: Environmental | L33: 141600 | M33: 14 | N33: 16 | O33: 0
A34: UPL | B34: Division 1 | C34: Upland_Control_Sites_Lower_Willamette | D34: Upland_Control_Sites_Lower_Willamette_Development | E34: Development | F34: 170000 | G34: 17 | H34: 0 | I34: 0 | K34: Survey | L34: 141800 | M34: 14 | N34: 18 | O34: 0
A35: UPL | B35: Division 1 | C35: Upland_Control_Sites_Lower_Willamette | E35: OutsideDesignServices | F35: 171510 | G35: 17 | H35: 15 | I35: 10 | K35: CAD | L35: 142200 | M35: 14 | N35: 22 | O35: 0
A36: UPL | B36: Division 1 | C36: Upland_Control_Sites_Lower_Willamette | D36: Upland_Control_Sites_Lower_Willamette_Implementation | E36: Implementation | F36: 180000 | G36: 18 | H36: 0 | I36: 0 | K36: BidPackage | L36: 142300 | M36: 14 | N36: 23 | O36: 0
A37: UPL | B37: Division 1 | C37: Upland_Control_Sites_Lower_Willamette | E37: RemedialAction | F37: 181000 | G37: 18 | H37: 10 | I37: 0 | K37: General | L37: 141000 | M37: 14 | N37: 10 | O37: 0
A38: UPL | B38: Division 1 | C38: Upland_Control_Sites_Lower_Willamette | E38: OandM_Systems | F38: 181100 | G38: 18 | H38: 11 | I38: 0 | K38: ESAReconsulation | L38: 142400 | M38: 14 | N38: 24 | O38: 0
A39: UPL | B39: Division 1 | C39: Upland_Control_Sites_Lower_Willamette | E39: OandM_Monitoring | F39: 181200 | G39: 18 | H39: 12 | I39: 0 | K39: UtilityRelocations | L39: 142500 | M39: 14 | N39: 25 | O39: 0
A40: UPL | B40: Division 1 | C40: Upland_Control_Sites_Lower_Willamette | D40: Upland_Control_Sites_Lower_Willamette_Construction | E40: Construction | F40: 190000 | G40: 19 | H40: 0 | I40: 0 | K40: Restoration | L40: 141500 | M40: 14 | N40: 15 | O40: 0
A41: UPL | B41: Division 1 | C41: Upland_Control_Sites_Lower_Willamette | E41: OutsideConstructionService | F41: 191810 | G41: 19 | H41: 18 | I41: 10 | K41: RestorationPlanandDev,includingDesign | L41: 141510 | M41: 14 | N41: 15 | O41: 10
A42: UPL | B42: Division 1 | C42: Upland_Control_Sites_Lower_Willamette | D42: Upland_Control_Sites_Lower_Willamette_Legal_Regulatory | E42: Legal_Regulatory | F42: 230000 | G42: 23 | H42: 0 | I42: 0 | K42: IdentityDevelopment | L42: 142900 | M42: 14 | N42: 29 | O42: 0
A43: UPL | B43: Division 1 | C43: Upland_Control_Sites_Lower_Willamette | E43: Pre_LitigationPreparation | F43: 231300 | G43: 23 | H43: 13 | I43: 0 | K43: PrintMedia | L43: 143000 | M43: 14 | N43: 30 | O43: 0
A44: UPL | B44: Division 1 | C44: Upland_Control_Sites_Lower_Willamette | E44: LitigationDefense | F44: 231400 | G44: 23 | H44: 14 | I44: 0 | K44: Event | L44: 143100 | M44: 14 | N44: 31 | O44: 0
A45: UPL | B45: Division 1 | C45: Upland_Control_Sites_Lower_Willamette | E45: ClosureReplort_NFA | F45: 231600 | G45: 23 | H45: 16 | I45: 0 | K45: Website | L45: 143200 | M45: 14 | N45: 32 | O45: 0
A46: UPL | B46: Division 1 | C46: Upland_Control_Sites_Lower_Willamette | E46: EnforcementDocuments | F46: 231700 | G46: 23 | H46: 17 | I46: 0 | K46: Photography | L46: 143300 | M46: 14 | N46: 33 | O46: 0
A47: UPL | B47: Division 1 | C47: Upland_Control_Sites_Lower_Willamette | E47: FiveYearReview | F47: 231800 | G47: 23 | H47: 18 | I47: 0 | K47: MultimediaPresentations | L47: 143400 | M47: 14 | N47: 34 | O47: 0
A48: UPL | B48: Division 1 | C48: Upland_Control_Sites_Lower_Willamette | E48: TenantCleanupOversight | F48: 232900 | G48: 23 | H48: 29 | I48: 0 | K48: SpecificationDevelopment | L48: 141100 | M48: 14 | N48: 11 | O48: 0
A49: UPL | B49: Division 1 | C49: Upland_Control_Sites_Lower_Willamette | D49: Upland_Control_Sites_Lower_Willamette_PublicRecordsRequest | E49: PublicRecordsRequest | F49: 240000 | G49: 24 | H49: 0 | I49: 0 | K49: RandD | L49: 141200 | M49: 14 | N49: 12 | O49: 0
A50: UPL | B50: Division 1 | C50: Upland_Control_Sites_Lower_Willamette | E50: General | F50: 241000 | G50: 24 | H50: 10 | I50: 0 | K50: DrawingandDevelopment | L50: 141900 | M50: 14 | N50: 19 | O50: 0
A51: UPL | B51: Division 1 | C51: Upland_Control_Sites_Lower_Willamette | D51: Upland_Control_Sites_Lower_Willamette_Outreach | E51: Outreach | F51: 250000 | G51: 25 | H51: 0 | I51: 0 | K51: PublicAffairs | L51: 142000 | M51: 14 | N51: 20 | O51: 0
A52: UPL | B52: Division 1 | C52: Upland_Control_Sites_Lower_Willamette | E52: General | F52: 251000 | G52: 25 | H52: 10 | I52: 0 | K52: Construction_InspectionSupport | L52: 142100 | M52: 14 | N52: 21 | O52: 0
A53: UPL | B53: Division 1 | C53: Upland_Control_Sites_Lower_Willamette | E53: CommunityRelations | F53: 251010 | G53: 25 | H53: 10 | I53: 10 | K53: ITDesignSupportContract | L53: 142600 | M53: 14 | N53: 26 | O53: 0
A54: UPL | B54: Division 1 | C54: Upland_Control_Sites_Lower_Willamette | D54: Upland_Control_Sites_Lower_Willamette_CostRecovery | E54: CostRecovery | F54: 300000 | G54: 30 | H54: 0 | I54: 0 | K54: Restore.PlanandDev,Incl.Des. | L54: 141510 | M54: 14 | N54: 15 | O54: 10
A55: UPL | B55: Division 1 | C55: Upland_Control_Sites_Lower_Willamette | E55: PRPPursuit | F55: 301000 | G55: 30 | H55: 10 | I55: 0 | K55: Planning | L55: 150000 | M55: 15 | N55: 0 | O55: 0
A56: UPL | B56: Division 1 | C56: Upland_Control_Sites_Lower_Willamette | D56: Upland_Control_Sites_Lower_Willamette_Payments | E56: Payments | F56: 320000 | G56: 32 | H56: 0 | I56: 0 | K56: AssessmentPlanning | L56: 151100 | M56: 15 | N56: 11 | O56: 0
A57: UPL | B57: Division 1 | C57: Upland_Control_Sites_Lower_Willamette | E57: PRPGroupPayments | F57: 321100 | G57: 32 | H57: 11 | I57: 0 | K57: PreliminaryAssessment | L57: 151110 | M57: 15 | N57: 11 | O57: 10
A58: UPL | B58: Division 1 | C58: Upland_Control_Sites_Lower_Willamette | E58: OversightCosts | F58: 321300 | G58: 32 | H58: 13 | I58: 0 | K58: SiteInvestigation | L58: 151200 | M58: 15 | N58: 12 | O58: 0
A59: UPL | B59: Division 1 | C59: Upland_Control_Sites_Lower_Willamette | E59: EPA | F59: 321310 | G59: 32 | H59: 13 | I59: 10 | K59: RemedialInvestigation | L59: 151300 | M59: 15 | N59: 13 | O59: 0
A60: UPL | B60: Division 1 | C60: Upland_Control_Sites_Lower_Willamette | E60: DEQ | F60: 321320 | G60: 32 | H60: 13 | I60: 20 | K60: CargillOU1 | L60: 151310 | M60: 15 | N60: 13 | O60: 10
A61: UPL | B61: Division 1 | C61: Upland_Control_Sites_Lower_Willamette | E61: Tribes | F61: 321330 | G61: 32 | H61: 13 | I61: 30 | K61: OU2 | L61: 151320 | M61: 15 | N61: 13 | O61: 20
A62: UPL | B62: Division 1 | C62: Upland_Control_Sites_Lower_Willamette | E62: Trustees | F62: 321340 | G62: 32 | H62: 13 | I62: 40 | K62: FeasibilityStudy | L62: 151600 | M62: 15 | N62: 16 | O62: 0
A63: UPL | B63: Division 1 | C63: Upland_Control_Sites_Lower_Willamette | D63: Upland_Control_Sites_Lower_Willamette_Contingency | E63: Contingency | F63: 790000 | G63: 79 | H63: 0 | I63: 0 | K63: CulturalResources | L63: 151700 | M63: 15 | N63: 17 | O63: 0
A64: UPL | B64: Division 1 | C64: Upland_Control_Sites_Lower_Willamette | E64: CASS | F64: 909000 | G64: 90 | H64: 90 | I64: 0 | K64: Strategy_Planning | L64: 151120 | M64: 15 | N64: 11 | O64: 20
A65: WIK | B65: Division 1 | C65: Work_in_Kind_Channel_Deepening | D65: Work_in_Kind_Channel_Deepening_ProjectAdminandMgmt | E65: ProjectAdminandMgmt | F65: 100000 | G65: 10 | H65: 0 | I65: 0 | K65: InjuryAssessment | L65: 151130 | M65: 15 | N65: 11 | O65: 30
A66: WIK | B66: Division 1 | C66: Work_in_Kind_Channel_Deepening | E66: General | F66: 101000 | G66: 10 | H66: 10 | I66: 0 | K66: General | L66: 151000 | M66: 15 | N66: 10 | O66: 0
A67: WIK | B67: Division 1 | C67: Work_in_Kind_Channel_Deepening | D67: Work_in_Kind_Channel_Deepening_Design | E67: Design | F67: 140000 | G67: 14 | H67: 0 | I67: 0 | K67: CapacityAnalysis | L67: 151140 | M67: 15 | N67: 11 | O67: 40
A68: WIK | B68: Division 1 | C68: Work_in_Kind_Channel_Deepening | E68: Environmental | F68: 141600 | G68: 14 | H68: 16 | I68: 0 | K68: EnvironmentalAssessment_ActionPlan | L68: 151150 | M68: 15 | N68: 11 | O68: 50
A69: WIK | B69: Division 1 | C69: Work_in_Kind_Channel_Deepening | E69: Survey | F69: 141800 | G69: 14 | H69: 18 | I69: 0 | K69: Forecasts | L69: 151400 | M69: 15 | N69: 14 | O69: 0
A70: WIK | B70: Division 1 | C70: Work_in_Kind_Channel_Deepening | E70: CAD | F70: 142200 | G70: 14 | H70: 22 | I70: 0 | K70: Cargo | L70: 151410 | M70: 15 | N70: 14 | O70: 10
A71: WIK | B71: Division 1 | C71: Work_in_Kind_Channel_Deepening | E71: BidPackage | F71: 142300 | G71: 14 | H71: 23 | I71: 0 | K71: FutureTechnology | L71: 151420 | M71: 15 | N71: 14 | O71: 20
A72: WIK | B72: Division 1 | C72: Work_in_Kind_Channel_Deepening | D72: Work_in_Kind_Channel_Deepening_Construction | E72: Construction | F72: 190000 | G72: 19 | H72: 0 | I72: 0 | K72: Capital | L72: 151430 | M72: 15 | N72: 14 | O72: 30
A73: WIK | B73: Division 1 | C73: Work_in_Kind_Channel_Deepening | E73: Contract | F73: 191000 | G73: 19 | H73: 10 | I73: 0 | K73: AlternativesDefinition | L73: 151500 | M73: 15 | N73: 15 | O73: 0
A74: WIK | B74: Division 1 | C74: Work_in_Kind_Channel_Deepening | E74: EquipmentContracts | F74: 191100 | G74: 19 | H74: 11 | I74: 0 | K74: Facility | L74: 151510 | M74: 15 | N74: 15 | O74: 10
A75: WIK | B75: Division 1 | C75: Work_in_Kind_Channel_Deepening | E75: Management | F75: 191200 | G75: 19 | H75: 12 | I75: 0 | K75: MasterPlan | L75: 151520 | M75: 15 | N75: 15 | O75: 20
A76: WIK | B76: Division 1 | C76: Work_in_Kind_Channel_Deepening | E76: Inspection | F76: 191300 | G76: 19 | H76: 13 | I76: 0 | K76: TransportationImprovement | L76: 151530 | M76: 15 | N76: 15 | O76: 30
A77: WIK | B77: Division 1 | C77: Work_in_Kind_Channel_Deepening | E77: Testing | F77: 191400 | G77: 19 | H77: 14 | I77: 0 | K77: IdentityDevelopment | L77: 152000 | M77: 15 | N77: 20 | O77: 0
A78: WIK | B78: Division 1 | C78: Work_in_Kind_Channel_Deepening | E78: Environmental | F78: 191600 | G78: 19 | H78: 16 | I78: 0 | K78: PrintMedia | L78: 152100 | M78: 15 | N78: 21 | O78: 0
A79: WIK | B79: Division 1 | C79: Work_in_Kind_Channel_Deepening | E79: EngineeringSupport | F79: 191800 | G79: 19 | H79: 18 | I79: 0 | K79: Event | L79: 152200 | M79: 15 | N79: 22 | O79: 0
A80: WIK | B80: Division 1 | C80: Work_in_Kind_Channel_Deepening | E80: NavigationSupport | F80: 192100 | G80: 19 | H80: 21 | I80: 0 | K80: Website | L80: 152300 | M80: 15 | N80: 23 | O80: 0
A81: WIK | B81: Division 1 | C81: Work_in_Kind_Channel_Deepening | E81: TenantAccess | F81: 192200 | G81: 19 | H81: 22 | I81: 0 | K81: Photography | L81: 152400 | M81: 15 | N81: 24 | O81: 0
A82: WIK | B82: Division 1 | C82: Work_in_Kind_Channel_Deepening | E82: OperatingDeptSupport | F82: 192300 | G82: 19 | H82: 23 | I82: 0 | K82: MultimediaPresentations | L82: 152500 | M82: 15 | N82: 25 | O82: 0
A83: WIK | B83: Division 1 | C83: Work_in_Kind_Channel_Deepening | D83: Work_in_Kind_Channel_Deepening_Permitting | E83: Permitting | F83: 200000 | G83: 20 | H83: 0 | I83: 0 | K83: GeneralStormWaterPipes | L83: 151240 | M83: 15 | N83: 12 | O83: 40
A84: WIK | B84: Division 1 | C84: Work_in_Kind_Channel_Deepening | E84: General | F84: 201000 | G84: 20 | H84: 10 | I84: 0 | K84: TechnicalSupport | L84: 151900 | M84: 15 | N84: 19 | O84: 0
A85: WIK | B85: Division 1 | C85: Work_in_Kind_Channel_Deepening | D85: Work_in_Kind_Channel_Deepening_Survey | E85: Survey | F85: 210000 | G85: 21 | H85: 0 | I85: 0 | K85: EE(SiteCharacterization) | L85: 151210 | M85: 15 | N85: 12 | O85: 10
A86: WIK | B86: Division 1 | C86: Work_in_Kind_Channel_Deepening | E86: Reconnaissance | F86: 211000 | G86: 21 | H86: 10 | I86: 0 | K86: EE_CAWorkPlan | L86: 151220 | M86: 15 | N86: 12 | O86: 20
A87: WIK | B87: Division 1 | C87: Work_in_Kind_Channel_Deepening | E87: Design | F87: 211100 | G87: 21 | H87: 11 | I87: 0 | K87: EE_CAPreparation | L87: 151230 | M87: 15 | N87: 12 | O87: 30
A88: WIK | B88: Division 1 | C88: Work_in_Kind_Channel_Deepening | E88: CAD | F88: 211300 | G88: 21 | H88: 13 | I88: 0 | K88: Assessment_Planning | L88: 151100 | M88: 15 | N88: 11 | O88: 0
A89: WIK | B89: Division 1 | C89: Work_in_Kind_Channel_Deepening | E89: BidPackage | F89: 211400 | G89: 21 | H89: 14 | I89: 0 | K89: Environ.Assess_ActionPlan | L89: 151150 | M89: 15 | N89: 11 | O89: 50
A90: WIK | B90: Division 1 | C90: Work_in_Kind_Channel_Deepening | E90: EngineeringSupport | F90: 211500 | G90: 21 | H90: 15 | I90: 0 | K90: TransportationAnalysis | L90: 151800 | M90: 15 | N90: 18 | O90: 0
A91: WIK | B91: Division 1 | C91: Work_in_Kind_Channel_Deepening | E91: OperatingDeptSupport | F91: 211600 | G91: 21 | H91: 16 | I91: 0 | K91: Acquisition | L91: 160000 | M91: 16 | N91: 0 | O91: 0
A92: WIK | B92: Division 1 | C92: Work_in_Kind_Channel_Deepening | D92: Work_in_Kind_Channel_Deepening_Maintenance | E92: Maintenance | F92: 220000 | G92: 22 | H92: 0 | I92: 0 | K92: General | L92: 161000 | M92: 16 | N92: 10 | O92: 0
A93: WIK | B93: Division 1 | C93: Work_in_Kind_Channel_Deepening | E93: Environmental | F93: 221000 | G93: 22 | H93: 10 | I93: 0 | K93: Demolition | L93: 161200 | M93: 16 | N93: 12 | O93: 0
A94: WIK | B94: Division 1 | C94: Work_in_Kind_Channel_Deepening | E94: EngineeringSupport | F94: 221100 | G94: 22 | H94: 11 | I94: 0 | K94: RelocationAssistance | L94: 161300 | M94: 16 | N94: 13 | O94: 0
A95: WIK | B95: Division 1 | C95: Work_in_Kind_Channel_Deepening | E95: OperatingDeptSupport | F95: 221200 | G95: 22 | H95: 12 | I95: 0 | K95: Appraisals | L95: 161400 | M95: 16 | N95: 14 | O95: 0
A96: WIK | B96: Division 1 | C96: Work_in_Kind_Channel_Deepening | E96: BidPackage | F96: 221300 | G96: 22 | H96: 13 | I96: 0 | K96: EnvironmentalAssessments | L96: 161500 | M96: 16 | N96: 15 | O96: 0
A97: WIK | B97: Division 1 | C97: Work_in_Kind_Channel_Deepening | E97: Monitoring | F97: 221400 | G97: 22 | H97: 14 | I97: 0 | K97: Condemnation | L97: 161600 | M97: 16 | N97: 16 | O97: 0
A98: WIK | B98: Division 1 | C98: Work_in_Kind_Channel_Deepening | D98: Work_in_Kind_Channel_Deepening_ProjectCloseOut | E98: ProjectCloseOut | F98: 780000 | G98: 78 | H98: 0 | I98: 0 | K98: Inspection | L98: 161700 | M98: 16 | N98: 17 | O98: 0
A99: WIK | B99: Division 1 | C99: Work_in_Kind_Channel_Deepening | E99: General | F99: 781000 | G99: 78 | H99: 10 | I99: 0 | K99: TitleWork | L99: 161800 | M99: 16 | N99: 18 | O99: 0
A100: WIK | B100: Division 1 | C100: Work_in_Kind_Channel_Deepening | D100: Work_in_Kind_Channel_Deepening_Contingency | E100: Contingency | F100: 790000 | G100: 79 | H100: 0 | I100: 0 | K100: Survey | L100: 162200 | M100: 16 | N100: 22 | O100: 0
...

Sheet Cost Codes
A1: SUBGROUP: GENERAL REQUIREMENTS
A2: Division 01 - General Requirements
A3: 13100 | B3: Contractor's Management and Coordination
A4: 13300 | B4: Submittal Procedures
A5: 13500 | B5: Security Control
A6: 13501 | B6: Escort
A7: 14100 | B7: Permits
A8: 15000 | B8: Mobilization and Demobilization
A9: 15001 | B9: Traffic Control
A10: 15002 | B10: Sweeping
A11: 15123 | B11: Temporary Heating, Cooling and Ventilating
A12: 15323 | B12: Temporary Ramps
A13: 15400 | B13: Construction Aids
A14: 15500 | B14: Vehicular Access and Parking
... A21: 19100 | B21: Commissioning
A22: SUBGROUP: FACILITY CONSTRUCTION
A23: Division 02 - Existing Conditions
A24: 20500 | B24: Common Work Results for Existing Conditions
A25: 24113 | B25: Site Demolition
A26: 24119 | B26: Selective Interior Demolition
A27: 25000 | B27: Site Remediation
A28: 26100 | B28: Removal and Disposal of Contaminated Soils
A29: 26500 | B29: Underground Storage Tank Removal
A30: 27100 | B30: Groundwater Treatment
A31: 28213 | B31: Asbestos Abatement
A32: 28216 | B32: Asbestos Management
A33: 28313 | B33: Lead-Based Paint Management
A34: 28319 | B34: Lead-Based Paint Abatement
A35: 28400 | B35: PCB Remediation
A36: Division 03 - Concrete
A37: 30500 | B37: Common Work Results for Concrete
A38: 31100 | B38: Concrete Formwork
A39: 31500 | B39: Concrete Accessories
A40: 32000 | B40: Concrete Reinforcing
A41: 33000 | B41: Cast-In-Place Concrete
A42: 36000 | B42: Concrete Grouting
A43: Division 04 - Masonry
A44: 40500 | B44: Common Work Results for Masonry
A45: 40513 | B45: Masonry Mortar and Grout
A46: 40523 | B46: Masonry Accessories
A47: 42113 | B47: Brick Masonry
A48: 42200 | B48: Concrete Unit Masonry
A49: Division 05 - Metals
A50: 50500 | B50: Common Work Results for Metals
A51: 50513 | B51: Galvanic Coatings
A52: 51200 | B52: Structural Steel Framing
A53: 51213 | B53: Architecturally Exposed Structural Steel Framing
A54: 52100 | B54: Steel Joist Framing
A55: 53100 | B55: Steel Decking
A56: 54000 | B56: Cold-Formed Metal Framing
A57: 55000 | B57: Metal Fabrications
A58: 55200 | B58: Metal Railings
A59: 57050 | B59: Stainless Steel Fabrications
A60: 57300 | B60: Glazed Decorative Metal Railings
A61: 57500 | B61: Decorative Formed Metal
A62: Division 06 - Wood, Plastics & Composites
A63: 60500 | B63: Common Work Results for Wood, Plastics & Composites
A64: 60100 | B64: Maintenance of Wood, Plastics, and Composites
A65: 61000 | B65: Rough Carpentry
A66: 61100 | B66: Framing and Sheathing
A67: 61400 | B67: Treated Wood for Roof Repairs
A68: 62000 | B68: Finish Carpentry
A69: 64000 | B69: Architectural Woodwork
A70: 64100 | B70: Custom Cabinets
A71: 64200 | B71: Wood Paneling
A72: 64600 | B72: Custom Casework
A73: 65113 | B73: Plastic Structural Lumber
A74: 66000 | B74: Plastic Fabrications
A75: Division 07 - Thermal and Moisture Protection
A76: 70500 | B76: Common Work Results for Thermal and Moisture Protection
A77: 70152 | B77: Modified Bituminous Sheet Roofing System Repairs
A78: 70153 | B78: Elastomeric Sheet Roofing System Repairs
A79: 71000 | B79: Waterproofing
A80: 71100 | B80: Damp proofing
A81: 71800 | B81: Traffic Coatings
A82: 72100 | B82: Thermal Insulation
A83: 72600 | B83: Vapor Retarders
A84: 72700 | B84: Air Barriers
A85: 74100 | B85: Roof Panels
A86: 74200 | B86: Wall Panels
A87: 75000 | B87: Membrane Roofing
... A98: 79500 | B98: Expansion Control
A99: Division 08 - Openings
A100: 80500 | B100: Common Work Results for Openings
A101: 80600 | B101: Door/Window Schedule
A102: 81100 | B102: Metal Doors and Frames
A103: 81400 | B103: Wood Doors
A104: 83100 | B104: Access Doors and Panels
A105: 83300 | B105: Coiling Doors and Grilles
A106: 83600 | B106: Panel Doors
A107: 84113 | B107: Aluminum Entrances and Storefronts
A108: 84126 | B108: All-Glass Entrances and Storefronts
A109: 84200 | B109: Entrance Door Systems
A110: 84400 | B110: Glazed Curtain Walls
A111: 85000 | B111: Windows
... A118: 89000 | B118: Louvers and Vents
A119: Division 09 - Finishes
A120: 90500 | B120: Common Work Results for Finishes
A121: 90600 | B121: Room Material and Finish Schedule
A122: 92100 | B122: Plaster and Gypsum Board Assemblies
...

Sheet UoM
B1: Hard Cost
B2: UoM | C2: % | D2: 1 | E2: Standard View
B3: UoM | C3: Acre | D3: 2 | E3: Engineering Planning View
B4: UoM | C4: CY | D4: 4
B5: UoM | C5: Day | D5: 5
B6: UoM | C6: Ea | D6: 6
B7: UoM | C7: Gal | D7: 7
B8: UoM | C8: Hr | D8: 8
B9: UoM | C9: Lb | D9: 9
B10: UoM | C10: LF | D10: 10
B11: UoM | C11: LS
B12: UoM | C12: SF
B13: UoM | C13: SY
B14: UoM | C14: Ton
B15: UoM | C15: Week
C16: Job

Sheet SoftCostUom
F1: Soft Cost
F2: UoM | G2: % | H2: 1
F3: UoM | G3: Week | H3: 2
F4: UoM | G4: Day | H4: 4
F5: UoM | G5: Hr | H5: 5
F6: UoM | G6: Ea | H6: 6
F7: UoM | G7: LS | H7: 7
G8: Job

Sheet Scope and Risk
E1: Risk Breakdown Structure | F1: Code
E2: People | F2: P
B3: Scope Accuracy: | C3: Level 1: Project scope well understood and well defined | D3: People | E3: PEOPLE: Unavailable resources - Engineering (P1) | F3: P1
B4: Scope Accuracy: | C4: Level 2: Project scope conceptual | D4: People | E4: PEOPLE: Unavailable resources - IT (P2) | F4: P2
B5: Scope Accuracy: | C5: Level 3: Project scope is a "vision" with limited detail | D5: People | E5: PEOPLE: Unavailable resources - Project (P3) | F5: P3
D6: People | E6: PEOPLE: Unavailable resources - Business (P4) | F6: P4
D7: People | E7: PEOPLE: Unavailable resources - Sponsor (P5) | F7: P5
B8: Engineering Effort: | C8: Level A: Preliminary engineering performed | D8: People | E8: PEOPLE: Difficulty staffing resources (P6) | F8: P6
B9: Engineering Effort: | C9: Level B: Conceptual engineering performed | D9: People | E9: PEOPLE: Loss of key people - Engineering (P7) | F9: P7
B10: Engineering Effort: | C10: Level C: No engineering performed | D10: People | E10: PEOPLE: Loss of key people - IT (P8) | F10: P8
D11: People | E11: PEOPLE: Loss of key people - Business (P9) | F11: P9
D12: People | E12: PEOPLE: Conflicts interfere with progress (P10) | F12: P10
D13: People | E13: PEOPLE: Resources lack required skills, experience, fit - Engineering (P11) | F13: P11
C14: Project Charter | D14: People | E14: PEOPLE: Resources lack required skills, experience, fit - IT (P12) | F14: P12
C15: Business Case - Gate 1 | D15: People | E15: PEOPLE: Resources lack required skills, experience, fit - Business (P13) | F15: P13
C16: Preliminary Design - Gate 2 | D16: People | E16: PEOPLE: Insufficient onboarding of new project staff (P14) | F16: P14
C17: 100% Design/ Pre-Bid - Gate 3 | D17: People | E17: PEOPLE: Human error (P15) | F17: P15
C18: Bid Acceptance - Gate 4 | D18: People | E18: PEOPLE: Project teams lacked sufficient understanding of new technology (P16) | F18: P16
C19: Project Closeout - Gate 5 | D19: People | E19: PEOPLE: Inability to scale specialty skills (P17) | F19: P17
D20: Requirements | E20: Requirements | F20: R
D21: Requirements | E21: REQUIREMENTS: Project outcomes or scope unclear (R1) | F21: R1
D22: Requirements | E22: REQUIREMENTS: Stakeholders not well understood (R2) | F22: R2
C23: Stage Gate 1 - Project Charter: +/-50% | D23: Requirements | E23: REQUIREMENTS: Error or omissions in requirements (R3) | F23: R3
C24: Stage Gate 2 - Business Case: +/-30% | D24: Requirements | E24: REQUIREMENTS: Significant learning, new ground (R4) | F24: R4
C25: Stage Gate 3 - Preliminary Planning: +/-25% | D25: Requirements | E25: REQUIREMENTS: Shifting business timelines, priorities (R5) | F25: R5
C26: Stage Gate 4a - 30% Design: -15% to +20% | D26: Requirements | E26: REQUIREMENTS: Inability to accurately translate business requirements into infrastructure scope (R6) | F26: R6
C27: Stage Gate 4a - 60% Design: -10% to +15% | D27: Requirements | E27: REQUIREMENTS: Unforeseen complexity or understanding of infrastructure (R7) | F27: R7
C28: Stage Gate 4a - 90% Design: +/-10% | D28: Requirements | E28: REQUIREMENTS: Mismatch of expectations between customers, sponsors, vendors (R8) | F28: R8
C29: Stage Gate 4b - CD Design: +/-5% | E29: Process | F29: PRC
D30: Process | E30: PROCESS: Poor work breakdown or estimating (PRC1) | F30: PRC1
C31: Percentage Based | D31: Process | E31: PROCESS: Operational processes not well understood (PRC2) | F31: PRC2
C32: Hourly Estimate | D32: Process | E32: PROCESS: Insufficient understanding of environmental complexity, dependencies (PRC3) | F32: PRC3
D33: Process | E33: PROCESS: Delays in reviews, approvals, decision-making problems (PRC4) | F33: PRC4
D34: Process | E34: PROCESS: Management or escalation problems (PRC5) | F34: PRC5
D35: Process | E35: PROCESS: Sliced work or unclear hand-offs (PRC6) | F35: PRC6
D36: Process | E36: PROCESS: Delivery methodology not well applied (PRC7) | F36: PRC7
D37: Process | E37: PROCESS: Unclear roles and responsibilities (PRC8) | F37: PRC8
D38: Process | E38: PROCESS: Gatekeepers or assessors lack skill, knowledge to make gate assessments/decisions (PRC9) | F38: PRC9
D39: Process | E39: PROCESS: Skill or accountability gap on complex end-to-end architecture/engineering solutions versus product solution (PRC10) | F39: PRC10
D40: Process | E40: PROCESS: Insufficient engagement to prepare estimates (PRC11) | F40: PRC11
D41: Process | E41: PROCESS: Project staff lacked sufficient understanding of Port processes (PRC12) | F41: PRC12
D42: Process | E42: PROCESS: Stakeholders responsibilities not well understood (PRC13) | F42: PRC13
D43: Process | E43: PROCESS: Changing process (PRC14) | F43: PRC14
D44: Process | E44: PROCESS: Insufficient of unclear process (PRC15) | F44: PRC15
... D51: Data | E51: DATA: Limited access to data (D4) | F51: D4
E52: Vendor | F52: V
D53: Vendor | E53: VENDOR: Resources lack sufficient depth of skills, experience, fit - Services vendor (V1) | F53: V1
D54: Vendor | E54: VENDOR: Unavailable resources - Services vendor (V2) | F54: V2
D55: Vendor | E55: VENDOR: Quality of goods not sufficient - Product vendor (V3) | F55: V3
D56: Vendor | E56: VENDOR: Procurement or contract problems (V4) | F56: V4
E57: Quality | F57: Q
D58: Quality | E58: QUALITY: Quality metrics not well understood (Q1) | F58: Q1
D59: Quality | E59: QUALITY: Inappropriate test plans (Q2) | F59: Q2
D60: Quality | E60: QUALITY: Insufficient testing (Q3) | F60: Q3
D61: Quality | E61: QUALITY: New, complex problems discovered (Q4) | F61: Q4
D62: Quality | E62: QUALITY: insufficient quality management expertise (Q5) | F62: Q5
D63: Quality | E63: QUALITY: Inconsistent use of quality tools (Q6) | F63: Q6
D64: Quality | E64: QUALITY: Inadequate design (Q7) | F64: Q7
E65: Technical | F65: TEC
D66: Technical | E66: TECHNICAL: Infrastructure not available (TEC1) | F66: TEC1
D67: Technical | E67: TECHNICAL: Complex physical infrastructure (TEC2) | F67: TEC2
D68: Technical | E68: TECHNICAL: Complex software infrastructure (TEC3) | F68: TEC3
D69: Technical | E69: TECHNICAL: Nonstandard Port tools, components, frameworks (TEC4) | F69: TEC4
D70: Technical | E70: TECHNICAL: Poor infrastructure performance (TEC5) | F70: TEC5
D71: Technical | E71: TECHNICAL: Complex interfaces with other systems (TEC6) | F71: TEC6
E72: Turnover | F72: TO
D73: Turnover | E73: TURNOVER: Client acceptance process is not clear or not approved (TO1) | F73: TO1
D74: Turnover | E74: TURNOVER: Required skill in people not ready (TO2) | F74: TO2
D75: Turnover | E75: TURNOVER: More support required than expected (TO3) | F75: TO3
D76: Turnover | E76: TURNOVER: Business turnover problems (TO4) | F76: TO4
D77: Turnover | E77: TURNOVER: IT support turnover problems (TO5) | F77: TO5
E78: Product | F78: PRO
D79: Product | E79: PRODUCT: Complex large design/development (PRO1) | F79: PRO1
D80: Product | E80: PRODUCT: Product quality problems (PRO2) | F80: PRO2
E81: Uncategorized | F81: U
D82: Uncategorized | E82: UNCATEGORIZED: Uncategorized risk - description required (U1) | F82: U1
E83: Construction
D84: Construction | E84: CONSTRUCTION: Potential survey error e.g. incorrect grades, locational error etc (C1) | F84: C1
D85: Construction | E85: CONSTRUCTION: Potential delay resulting from the Private Utilities being tardy in relocating utilities (C2) | F85: C2
D86: Construction | E86: CONSTRUCTION: Unforeseen site conditions (utilities, environmental etc) during construction (C3) | F86: C3
D87: Construction | E87: CONSTRUCTION: Differential settlement to properties due to work; impacts to design and construction (C4) | F87: C4
D88: Construction | E88: CONSTRUCTION: Cost escalation (of materials/equipment) during construction period (C5) | F88: C5
D89: Construction | E89: CONSTRUCTION: Risk that price of steel may increase prior to order by contractor (C6) | F89: C6
D90: Construction | E90: CONSTRUCTION: Additional streetscape or stormwater requirements (C7) | F90: C7
F91: C8
F92: C9
F93: C10
F94: C11
